Workbook

Sheet DATOS
A1: ESTUDIANTE | B1: PREGRADO | C1: MODALIDAD | D1: POSGRADO | E1: PROFESOR GUIA | F1: PROFESOR COGUIA | G1: TITULO | H1: ANIO PUBLICACION | I1: LICENCIA | J1: AUTORIZACION | K1: ¿EXISTE RESUMEN? | L1: CHECKLIST | M1: RESUMEN | N1: ENLACE | O1: UNIVERSIDAD | P1: DEPARTAMENTO | Q1: AREA_APLICACION | R1: AREA_CONOCIMIENTO | S1: KEYWORDS | T1: AREA_SWEBOK
A2: JUAN PABLO REYES SEPÚLVEDA | B2: INGENIERÍA DE EJECUCIÓN EN COMPUTACIÓN E INFORMÁTICA | C2: VESPERTINA | E2: LUIS RÍOS SEPÚLVEDA | G2: Prototipo de sistema web de apoyo a la gestión de máquinas virtuales en la empresa ADESSA Ltda. | H2: 2015 | I2: Creative Commons AtribuciónNoComercial | J2: AUTORIZADO | K2: SI | L2: =IF(K2 = "SI", EXTRA!$C$3, EXTRA!$C$4) | M2: En este trabajo de título se presenta el desarrollo de un prototipo web de apoyo a la gestión de máquinas virtuales (en adelante, MV) para el área de plataforma de virtualización de la empresa ADESSA Ltda., con el fin de mejorar el actual proceso que involucra la gestión de solicitudes de MV, el cual ha presentado una degradación en el servicio debido al aumento sostenido en la demanda de MV de los clientes de la empresa ADESSA Ltda. Para ello, se diseña e implementa un prototipo que permita obtener indicadores sobre gestión de solicitudes de creación, modificación y eliminación de MV, aportando además a los actores involucrados, información que les permita apoyar la toma decisiones, todo lo anterior en el marco que involucra al área de plataforma de virtualización de ADESSA Ltda. Se hace uso de la metodología OMT++, dado que se trata de un problema mediano en la parte de software y con requerimientos claros desde el principio. El prototipo será puesto a prueba durante el segundo semestre del presente año, donde se espera que al final de dicho período se cuenten con los indicadores que permitan identificar las fortalezas y debilidades del actual proceso de gestión que tiene en la actualidad la plataforma de virtualización. Para poder tomar finalmente como input el prototipo para el desarrollo del sistema final. | N2: https://usach.primo.exlibrisgroup.com/discovery/delivery/56USACH_INST:REPOSITORIO/1226582910006116 | O2: UNIVERSIDAD DE SANTIAGO DE CHILE | P2: DEPARTAMENTO DE INGENIERÍA INFORMÁTICA | Q2: (7) Computer Science | R2: (14) Software Development Fundamentals | S2: gestión, mv, prototipo, adessa, ltda, plataforma, virtualización, actual, desarrollo, empresa | T2: (3) Software Design
A3: ADOLFO ESTEBAN DÍAZ MORALES | B3: INGENIERÍA CIVIL EN INFORMÁTICA | C3: DIURNA | E3: MÓNICA VILLANUEVA ILUFI | G3: Enumeración de conjuntos independientes maximales en grafos tipo Grilla | H3: 2015 | I3: SIN LICENCIA | J3: SIN AUTORIZACIÓN | K3: NO | L3: =IF(K3 = "SI", EXTRA!$C$3, EXTRA!$C$4) | N3: https://usach.primo.exlibrisgroup.com/discovery/delivery/56USACH_INST:REPOSITORIO/1241018680006116 | O3: UNIVERSIDAD DE SANTIAGO DE CHILE | P3: DEPARTAMENTO DE INGENIERÍA INFORMÁTICA | Q3: (28) It does not belong to the computer science field. | R3: (18) It does not belong to the computer science field. | S3: NA | T3: (20) It does not belong to the computer science field.
A4: GABRIEL OSVALDO GÓMEZ ABARCA | B4: INGENIERÍA DE EJECUCIÓN EN COMPUTACIÓN E INFORMÁTICA | C4: VESPERTINA | E4: LUIS RÍOS SEPÚLVEDA | G4: Sistema de monitoreo y alertas para plataformas de servicio en entorno virtual VMWARE | H4: 2015 | I4: Atribución Creative Commons | J4: AUTORIZADO | K4: SI | L4: =IF(K4 = "SI", EXTRA!$C$3, EXTRA!$C$4) | M4: El siguiente trabajo describe el desarrollo de un sistema de apoyo al monitoreo de las plataformas virtuales VMware tanto a nivel de centro de datos como también de computación en la nube, estableciendo para ello su desarrollo sobre plataformas de código abierto y explotado funcionalidades de otras herramientas, como lo es para este caso el motor de Nagios. Durante la evolución del trabajo, las distintas realidades y necesidades de implementación son desarrolladas en base a la metodología de la programación extrema, lo cual permitió a lo largo del proceso de construcción del software, la versatilidad necesaria para construir un sistema funcional, de alto impacto operacional y de nulo coste de implementación, lo que pretende establecer esta herramienta como una alternativa válida para plataformas productivas o de servicios virtualizados sobre VMware. | N4: https://usach.primo.exlibrisgroup.com/discovery/delivery/56USACH_INST:REPOSITORIO/1226596040006116 | O4: UNIVERSIDAD DE SANTIAGO DE CHILE | P4: DEPARTAMENTO DE INGENIERÍA INFORMÁTICA | Q4: (7) Computer Science | R4: (16) Specialized Platform Development | S4: plataformas, desarrollo, implementación, sistema, trabajo, vmware, abierto, alternativa, alto, apoyo | T4: (3) Software Design
A5: GUSTAVO ADOLFO REYES ASPÉ | B5: INGENIERÍA DE EJECUCIÓN EN COMPUTACIÓN E INFORMÁTICA | C5: VESPERTINA | E5: RICARDO CONTRERAS SEPÚLVEDA | G5: Desarrollo de un sistema de información administrativa que apoya la coordinación docente departamental de la Facultad de Ingeniería | H5: 2015 | I5: Creative Commons ReconocimientoNoComercialCompartirIgual | J5: AUTORIZADO | K5: SI | L5: =IF(K5 = "SI", EXTRA!$C$3, EXTRA!$C$4) | M5: El objetivo principal del presente Trabajo de Titulación es el desarrollo de un sistema de información administrativo, que apoye la Coordinación Docente Departamental dentro de la Facultad de Ingeniería de la Universidad de Santiago de Chile. Actualmente, los actores involucrados en la coordinación docente en la Facultad de Ingeniería de la Universidad de Santiago de Chile, utilizan un sistema de información que presenta ciertos inconvenientes en el procesamiento y presentación de la información, dificultando la interacción y operación de los usuarios con el mismo, provocando mermas en la productividad, complejidad innecesaria y retrasos en el proceso global. El sistema desarrollado es una aplicación Web, que a través de una serie de módulos, entrega el apoyo necesario a los actores involucrados en la coordinación, para realizar, por ejemplo, la definición de cursos, asignación de profesores y ayudantes, inscripción de asignaturas por alumno, administración de inscripciones, consulta de información respecto a alumnos, entre otros. Para el desarrollo esta solución, se ha utilizado la metodología orientada a objetos OMT++. A través de la aplicación de la misma, se expone una descripción detallada de los requerimientos, así como de los casos de uso que definen las funcionalidades esenciales del sistema, los cuales son parte fundamental de las entradas para las etapas análisis y diseño de la herramienta. El presente Trabajo de Titulación ha generado una herramienta multiplataforma, que cumple con la totalidad de los requisitos funcionales y no funcionales recolectados, que reduce los tiempos y la complejidad, permitiendo un desenvolvimiento fluido, coherente y eficiente entre sus distintos módulos, convirtiéndose en un mayor apoyo para los involucrados en el proceso de Coordinación Docente. | N5: https://usach.primo.exlibrisgroup.com/discovery/delivery/56USACH_INST:REPOSITORIO/1249698290006116 | O5: UNIVERSIDAD DE SANTIAGO DE CHILE | P5: DEPARTAMENTO DE INGENIERÍA INFORMÁTICA | Q5: (7) Computer Science | R5: (14) Software Development Fundamentals | S5: coordinación, información, sistema, docente, involucrados, actores, aplicación, apoyo, chile, complejidad | T5: (3) Software Design
A6: VICTOR JOSÉ LEBIL LEGUE | B6: INGENIERÍA DE EJECUCIÓN EN COMPUTACIÓN E INFORMÁTICA | C6: VESPERTINA | E6: CAROLINA BONACIC CASTRO | G6: Aplicación de apoyo al proceso de gestión de servicios de taller | H6: 2015 | I6: Creative Commons AtribuciónNoComercial | J6: AUTORIZADO | K6: SI | L6: =IF(K6 = "SI", EXTRA!$C$3, EXTRA!$C$4) | M6: El presente trabajo, se enfoca en la problemática que ocurre en el área de servicios (gestión del taller) de la organización “Autobahn S.A.”. La empresa ha tenido estos inconvenientes desde que se implementó el actual sistema SAP Business One. El principal problema del sistema SAP Business One, es que está orientado a cubrir las principales áreas de una empresa de ventas de productos; finanzas, ventas, compras, inventario, etc., sin abarcar el área de servicio de una empresa. Se aborda dicha problemática, a través del desarrollo de un sistema en ambiente Web, que permita gestionar los servicios de control del taller, mediante la asignación de instaladores a los vehículos detallados en las órdenes de ventas, detalle de estacionamientos, etc. Para el desarrollo de la solución, se utilizan las distintas etapas de la metodología basada en el paradigma de orientación a objetos, OMT++. Finalmente, el sistema permite controlar y realizar seguimiento de todos los vehículos que se encuentran en el taller, mejorando los tiempos de respuesta en cuanto la información requerida, no solo en el área del taller, sino que también en otras áreas de la empresa. | N6: https://usach.primo.exlibrisgroup.com/discovery/delivery/56USACH_INST:REPOSITORIO/1226580850006116 | O6: UNIVERSIDAD DE SANTIAGO DE CHILE | P6: DEPARTAMENTO DE INGENIERÍA INFORMÁTICA | Q6: (7) Computer Science | R6: (14) Software Development Fundamentals | S6: empresa, sistema, taller, ventas, área, business, desarrollo, etc, one, problemática | T6: (3) Software Design
A7: AILEEN LISSETTE ESPARZA VILLAMÁN | B7: INGENIERÍA CIVIL EN INFORMÁTICA | C7: DIURNA | D7: MAGÍSTER EN INGENIERÍA INFORMÁTICA | E7: ROBERTO GONZÁLEZ-IBÁÑEZ | G7: Detección implícita de relevancia percibida de páginas web utilizando registros de actividad del usuario en la búsqueda de información | H7: 2015 | I7: TODOS LOS DERECHOS RESERVADOS | J7: AUTORIZADO | K7: NO | L7: =IF(K7 = "SI", EXTRA!$C$3, EXTRA!$C$4) | N7: https://usach.primo.exlibrisgroup.com/discovery/delivery/56USACH_INST:REPOSITORIO/1226577500006116 | O7: UNIVERSIDAD DE SANTIAGO DE CHILE | P7: DEPARTAMENTO DE INGENIERÍA INFORMÁTICA | Q7: (28) It does not belong to the computer science field. | R7: (18) It does not belong to the computer science field. | S7: NA | T7: (20) It does not belong to the computer science field.
A8: ALEX MAURICIO POBLETE GONZÁLEZ | B8: INGENIERÍA DE EJECUCIÓN EN COMPUTACIÓN E INFORMÁTICA | C8: VESPERTINA | E8: ANDRÉS RICE MORA | G8: Sistema de evaluación interactivo con dispositivos smartphone | H8: 2015 | I8: Creative Commons AtribuciónNoComercial | J8: AUTORIZADO | K8: SI | L8: =IF(K8 = "SI", EXTRA!$C$3, EXTRA!$C$4) | M8: En el presente trabajo de titulación se aborda el problema existente en la Universidad de Santiago de Chile, que se refiere a las tecleras por radio frecuencia, las cuales no están prestando la utilidad prevista, ni están cumpliendo con los objetivos planeados inicialmente para los profesores de la Universidad, los que consistían en hacer un seguimiento del aprendizaje de los alumnos a lo largo del semestre y facilitar la exposición de las materias en clases. Dada la problemática presentada, es que se realiza un análisis y diseño de sistema, que conduce a la construcción de un prototipo que permita a los profesores realizar un correcto seguimiento del avance del proceso de enseñanza-aprendizaje de los estudiantes. La solución planteada es desarrollar una alternativa a las tecleras por radio frecuencia, mediante la utilización de dispositivos móviles (smartphone) y una aplicación de escritorio que permita a los profesores realizar cuestionarios con distintas alternativas y exponerlas en clases para que los estudiantes, puedan realizar la votación a las preguntas expuestas por el profesor. En el presente documento se presenta el proceso de desarrollo del sistema, basándose en un paradigma orientado a objetos y en la utilización de la técnica OMT++, que define la estructura de este documento, especificando para cada una de sus fases los productos generados. Los resultados obtenidos al finalizar el proyecto cumplen con el objetivo general planteado para el proyecto y satisfacen las necesidades especificadas por Unidad de Innovación Educativa (UNIE) de la Universidad de Santiago de Chile. | N8: https://usach.primo.exlibrisgroup.com/discovery/delivery/56USACH_INST:REPOSITORIO/1226483070006116 | O8: UNIVERSIDAD DE SANTIAGO DE CHILE | P8: DEPARTAMENTO DE INGENIERÍA INFORMÁTICA | Q8: (7) Computer Science | R8: (14) Software Development Fundamentals | S8: profesores, realizar, universidad, aprendizaje, chile, clases, documento, estudiantes, frecuencia, permita | T8: (3) Software Design
A9: BASTIÁN FELIPE GANGA PEÑA | B9: INGENIERÍA DE EJECUCIÓN EN COMPUTACIÓN E INFORMÁTICA | C9: VESPERTINA | E9: ROSA MUÑOZ CALANCHIE | G9: Aplicación interactiva sobre dispositivo Touch-Screen, con el objetivo de mejorar la atención de clientes en Delightchile | H9: 2015 | I9: Atribución Creative Commons | J9: AUTORIZADO | K9: SI | L9: =IF(K9 = "SI", EXTRA!$C$3, EXTRA!$C$4) | M9: La medición de la calidad de atención al cliente se ha convertido en una herramienta importante para evaluar los protocolos de atención de las empresas, detectando fortalezas y debilidades, cuyos resultados son de gran utilidad para tomar medidas de mitigación con el objetivo de marcar la diferencia con otras marcas de la competencia, logrando fidelizar a sus clientes y captar nuevos. Para las empresas, es importante contar con esta información lo más pronto posible, lo que se complica cuando no existe ningún sistema que pueda entregar esta información. Para ello es que el objetivo de este trabajo de titulación, desarrollar un sistema informático interactivo y que cuenta con un sistema de evaluación de atención hacia los clientes. Para realizar este proyecto se utilizó una metodología basada en un modelo de desarrollo de Prototipos de software, modelo adecuado cuando el cliente tiene claro los objetivos generales del sistema, pero éste no identifica los requisitos detallados de entrada, procedimiento o salida. Es un modelo de desarrollo evolutivo, en el que el prototipo debe ser construido en poco tiempo, realizando entregas periódicas para su revisión y posteriores mejoras, hasta llegar al prototipo final utilizando pocos recursos. Como resultado del desarrollo, se obtiene un software que cumple con las características de un sistema embebido diseñado para cubrir las necesidades específicas de la empresa, además de ser portable y accesible con o sin Internet dentro de un sistema touch screen. Finalmente, uno de los aspectos que se destacan en la implementación del sistema, es el módulo de catálogo de productos que ofrece una auto atención para los clientes que visitan las distintas sucursales de DelightChile, apoyando así el proceso de atención de estos, se reducen los tiempos de espera y se evitan las filas de atención para los clientes. También con el nuevo software se comienza a conocer como son atendidos los clientes, ya que estos deben evaluar el desempeño de los vendedores en las sucursales, llenando los formularios y calificandolos con una nota de 1 a 5. | N9: https://usach.primo.exlibrisgroup.com/discovery/delivery/56USACH_INST:REPOSITORIO/1226636460006116 | O9: UNIVERSIDAD DE SANTIAGO DE CHILE | P9: DEPARTAMENTO DE INGENIERÍA INFORMÁTICA | Q9: (7) Computer Science | R9: (15) Software Engineering | S9: sistema, atención, clientes, desarrollo, modelo, software, cliente, empresas, evaluar, importante | T9: (3) Software Design
A10: FELIPE ALEJANDRO LAGOS BECERRA | B10: INGENIERÍA DE EJECUCIÓN EN COMPUTACIÓN E INFORMÁTICA | C10: VESPERTINA | E10: LUIS RÍOS SEPÚLVEDA | G10: Sistema web de apoyo a la gestión de franquicias médicas-dentales para alumnos de la Universidad de Chile | H10: 2015 | I10: Creative Commons AtribuciónNoComercial | J10: AUTORIZADO | K10: SI | L10: =IF(K10 = "SI", EXTRA!$C$3, EXTRA!$C$4) | M10: En este trabajo de titulación se presenta el diseño e implementación de un sistema, para dar solución al problema en la asignación de franquicias médicas y dentales que son beneficios otorgados a alumnos de la Universidad de Chile. Dicho problema se genera debido a ubicación geográfica de los centros de atención, ya que los diversos actores no visualizan el estado de la solicitud del beneficio, implicando dificultades comunicacionales. El sistema que se diseña e implementa como solución de apoyo a la gestión de franquicias médicas – dentales, y agiliza el flujo para una mejor entrega del beneficios. Para desarrollar este sistema, se utiliza el paradigma orientado a objetos y basado en la metodología OMT++, la cual, comienza con la toma de requerimientos, finalizando con las pruebas al sistema, con lo que se obtiene el producto requerido. | N10: https://usach.primo.exlibrisgroup.com/discovery/delivery/56USACH_INST:REPOSITORIO/1226601990006116 | O10: UNIVERSIDAD DE SANTIAGO DE CHILE | P10: DEPARTAMENTO DE INGENIERÍA INFORMÁTICA | Q10: (7) Computer Science | R10: (15) Software Engineering | S10: sistema, beneficios, dentales, franquicias, médicas, problema, solución, actores, agiliza, alumnos | T10: (3) Software Design
A11: JUAN PABLO VERDEJO JORQUERA | B11: INGENIERÍA DE EJECUCIÓN EN COMPUTACIÓN E INFORMÁTICA | C11: VESPERTINA | E11: FERNANDO RANNOU FUENTES | G11: Herramienta de diseño de configuraciones atómicas y visualización de resultados para simulación de campo magnético | H11: 2015 | I11: Creative Commons AtribuciónNoComercialCompartirIgual | J11: AUTORIZADO | K11: SI | L11: =IF(K11 = "SI", EXTRA!$C$3, EXTRA!$C$4) | M11: Investigadores del Departamento de Física de la Universidad de Santiago de Chile simulan los efectos del campo magnético en los átomos de distintos objetos. El proceso de diseño de configuraciones atómicas y de visualización de resultados de aquellas simulaciones es manual, lo que hace que el tiempo necesario para ejecutar dichas tareas sea alto. Es necesario desarrollar una aplicación que permita mejorar los procesos actuales, tanto de diseño de configuraciones atómicas como de visualización de los resultados. Para solucionar este problema, se diseña y crea una aplicación en Python que permite diseñar rápidamente las configuraciones atómicas con todas sus características físicas. Estas configuraciones atómicas pueden ser validadas inmediatamente mediante una visualización 3D generada con OpenGL y descargadas como imagen para publicaciones. La herramienta permite, además, visualizar los resultados de la simulación en 3D analizando los vectores de magnetización para cada átomo en cada uno de los pasos Monte Carlo ejecutados en la simulación. Estos resultados pueden ser exportados para publicaciones o conferencias como imágenes o videos. El desarrollo se basa en una modificación a la metodología Scrum. Estas son necesarias, ya que la metodología está pensada para equipos de desarrollo compuestos por ma ́s de una persona. Dichas modificaciones se refieren, principalmente, a las distintas reuniones del equipo de desarrollo que la metodología define, también conocidas como ceremonias en la terminología Scrum, y que fueron adaptadas para este caso particular. La aplicación desarrollada está siendo usada actualmente por dos alumnos de doctorado en sus tesis. Esto ha permitido que tareas que anteriormente tomaban horas, incluso días, puedan ser ejecutadas en solo minutos. Gracias a esto, los investigadores disponen de más tiempo para analizar los resultados, que pueden ser utilizados en nuevas aplicaciones que nos permitan avanzar como sociedad. | N11: https://usach.primo.exlibrisgroup.com/discovery/delivery/56USACH_INST:REPOSITORIO/1226531300006116 | O11: UNIVERSIDAD DE SANTIAGO DE CHILE | P11: DEPARTAMENTO DE INGENIERÍA INFORMÁTICA | Q11: (24) Physics and Astronomy | R11: (16) Specialized Platform Development | S11: resultados, atómicas, configuraciones, ser, aplicación, desarrollo, metodología, pueden, visualización, cada | T11: (3) Software Design
A12: CRISTOPHER ERNESTO MUÑOZ SANDOVAL | B12: INGENIERÍA DE EJECUCIÓN EN COMPUTACIÓN E INFORMÁTICA | C12: VESPERTINA | E12: MÓNICA VILLANUEVA ILUFI | G12: Enumeración de conjuntos independientes maximales en gráficos K-Tree | H12: 2015 | I12: Creative Commons AtribuciónNoComercialCompartirIgual | J12: AUTORIZADO | K12: SI | L12: =IF(K12 = "SI", EXTRA!$C$3, EXTRA!$C$4) | M12: En 1984 Leung resuelve el problema de enumeración de conjuntos independientes maximales (cim) en grafos cordales (también llamados triangulados), creando un algoritmo con complejidad temporal de orden O((n + e) * m) , siendo n el número de nodos, e el número de aristas y m el número de conjuntos independientes maximales. Un grafo completo con k nodos es un grafo perteneciente a la clase k-tree, dado un k fijo. Si G es un k-tree y C es un k-clique de G, entonces el grafo formado al añadir un nuevo vértice a G, y haciéndolo adyacente a todos los nodos de C, es un k-tree. El presente trabajo aborda el problema de la enumeración de conjuntos independientes maximales en grafos k-tree, una subclase de los grafos cordales. Si bien el algoritmo de Leung es efectivo para los grafos k-tree, estos últimos poseen la “propiedad constructiva” que en palabras simples dice que un grafo k-tree puede ser formado añadiendo nodos a otro grafo k- tree inicial. En base a esto el presente trabajo toma el siguiente enfoque: Sea G un grafo perteneciente a la clase k-tree, y sea CIM(G) su familia de conjuntos independientes maximales. Si se añade un nuevo nodo v a G, haciéndolo adyacente al algún k-clique de G, obteniendo el grafo G+v, ¿es posible obtener los conjuntos independientes maximales de G+v a partir de CIM(G)? Como resultado de este trabajo se presenta un algoritmo que, en base a los conjuntos independientes maximales de un grafo k-tree, enumera la familia de conjuntos independientes maximales al agregar un nuevo nodo al grafo. El algoritmo desarrollado tiene una complejidad temporal de orden O(m2 * n). | N12: https://usach.primo.exlibrisgroup.com/discovery/delivery/56USACH_INST:REPOSITORIO/1226544890006116 | O12: UNIVERSIDAD DE SANTIAGO DE CHILE | P12: DEPARTAMENTO DE INGENIERÍA INFORMÁTICA | Q12: (7) Computer Science | R12: (1) Algorithms and Complexity | S12: k, g, grafo, tree, conjuntos, independientes, maximales, algoritmo, grafos, nodos | T12: (19) Research/Investigation
A13: ARTURO MENDOZA URTEAGA | B13: INGENIERÍA CIVIL EN INFORMÁTICA | C13: VESPERTINA | E13: EDMUNDO LEIVA LOBOS | G13: Sistema de captura sincronizada de registros multimodales de la interacción humana computador para posteriormente reconocer episodios de sonrisa | H13: 2015 | I13: Creative Commons AtribuciónNoComercialCompartirIgual | J13: AUTORIZADO | K13: SI | L13: =IF(K13 = "SI", EXTRA!$C$3, EXTRA!$C$4) | M13: El presente trabajo de titulación tiene por objetivo desarrollar la primera versión de un ambiente de experimentación basado en un mecanismo de sincronización y visualización de videos para el reconocimiento de patrones que aparecen en las sonrisas. Esta solución se ha desarrollado como respuesta a los procesos que un experto de la computación afectiva realiza en el contexto de la detección del engaño cuando la gente sonríe. Dicho esto, el problema de sincronizar videos para los distintos canales resulta ineficiente si son efectuados a través de procesos manuales. En el mundo real, los protocolos de pregunta/respuesta establecidos por policías, seleccionadores de recursos humanos, investigadores y terapeutas para llevar a los sujetos a tener contradicciones son comúnmente acompañados de sonrisas que a su vez dan indicios de engaño, pero es preciso analizarlas en detalle. El prototipo asociado a esta memoria fue construido con la metodología RAD y utiliza patrón de diseño MVC garantizando que el ambiente sea escalable en el tiempo. La solución consistió en inicializar u organizar los aspectos temporales de la información transportada en un sistema de múltiples canales pero solamente cuando los canales puedan ser llevados a videos. En su uso real, la aplicación espera que el sujeto sonría después de una pregunta de un caza mentiras (que está conectado por video conferencia). En uso de investigación, el proceso genera archivos físicos “logs” que pueden ser utilizados por el investigador en computación afectiva para el análisis a posteriori de datos capturados. Por otro lado, la visualización de videos consistió en un reproductor web que permite cargar videos y reproducirlos de forma simultánea. En resumen, el software construido permite la captura del rostro de la persona frente al monitor (FaceRecorder), lo que él o ella enfoca su atención sobre la pantalla (EyeTribe) y lo que muestra la interfaz (ActivityRender). | N13: https://usach.primo.exlibrisgroup.com/discovery/delivery/56USACH_INST:REPOSITORIO/1226518900006116 | O13: UNIVERSIDAD DE SANTIAGO DE CHILE | P13: DEPARTAMENTO DE INGENIERÍA INFORMÁTICA | Q13: (7) Computer Science | R13: (15) Software Engineering | S13: videos, canales, afectiva, ambiente, computación, consistió, construido, engaño, permite, pregunta | T13: (3) Software Design
A14: ALONSO LEONIDAS INOSTROSA PSIJAS | B14: - | D14: DOCTORADO EN CIENCIAS DE LA INGENIERÍA, MENCIÓN INGENIERÍA INFORMÁTICA | E14: JUAN MAURICIO MARÍN CAIHUAN | F14: GRACIELA VERÓNICA GIL COSTA | G14: Simulaciones aproximadas semi-asíncronas en Devs con aplicación en motores de búsqueda web | H14: 2015 | I14: SIN LICENCIA | J14: SIN AUTORIZACIÓN | K14: NO | L14: =IF(K14 = "SI", EXTRA!$C$3, EXTRA!$C$4) | N14: https://usach.primo.exlibrisgroup.com/discovery/delivery/56USACH_INST:REPOSITORIO/1249699810006116 | O14: UNIVERSIDAD DE SANTIAGO DE CHILE | P14: DEPARTAMENTO DE INGENIERÍA INFORMÁTICA | Q14: (28) It does not belong to the computer science field. | R14: (18) It does not belong to the computer science field. | S14: NA | T14: (20) It does not belong to the computer science field.
A15: FERNANDO ANTONIO RODRÍGUEZ HERRERA | B15: INGENIERÍA CIVIL EN INFORMÁTICA | C15: VESPERTINA | E15: ALCIDES QUISPE SANCA | G15: Rediseño y propuesta de software para la gestión del proceso realizado en el cobro de facturas de servicios de proveedores en una inmobiliaria | H15: 2015 | I15: Atribución Creative Commons | J15: AUTORIZADO | K15: SI | L15: =IF(K15 = "SI", EXTRA!$C$3, EXTRA!$C$4) | M15: Este trabajo de titulación coloca a disposición de la comunidad, el cómo se rediseñó el proceso que realizaba el Departamento de Contabilidad de una inmobiliaria, para hacer efectivo el cobro por servicios prestados por proveedores de las obras que tiene en funcionamiento y el desarrollo de un sistema de software, el cual permite gestionar el proceso completo. Se inició el rediseño del proceso, realizando un análisis y modelamiento de éste en BPMN (Modelo y Notación de Procesos de Negocio), lo cual permitió identificar todas las tareas y roles. Posteriormente ya teniendo el modelo del proceso, se identificaron las problemáticas que afectan a éste, de manera de atacar estos problemas desde su raíz, lo cual se logró reorganizando tareas y roles, agregando y eliminando tareas del proceso. Una vez obtenido el nuevo proceso, este fue utilizado como columna vertebral en el desarrollo del sistema de software, el cual se encuentra dividido en una interfaz de escritorio y una Web. De estas dos interfaces se desarrollada únicamente la primera de éstas, utilizando para esto la metodología ágil scrum. La aplicación desarrollada es utilizada dentro de las dependencias de la empresa por la recepcionista y las administrativas de proveedores, para gestionar las facturas, notas de crédito y cartas de factoraje recibidas y generar los envíos a aprobación de las facturas, de manera que la obra indique si el cobro corresponde y hacerlo efectivo. Finalmente, el trabajo concluye con la medición del grado de satisfacción que tienen los usuarios con el nuevo proceso de cobro y el sistema de software que lo gestiona. | N15: https://usach.primo.exlibrisgroup.com/discovery/delivery/56USACH_INST:REPOSITORIO/1226569580006116 | O15: UNIVERSIDAD DE SANTIAGO DE CHILE | P15: DEPARTAMENTO DE INGENIERÍA INFORMÁTICA | Q15: (4) Business, Management and Accounting | R15: (15) Software Engineering | S15: proceso, cobro, sistema, software, tareas, desarrollada, desarrollo, efectivo, facturas, gestionar | T15: (3) Software Design
A16: JAVIER ANDRÉS HENRÍQUEZ ACEVEDO | B16: INGENIERÍA CIVIL EN INFORMÁTICA | C16: VESPERTINA | E16: MÓNICA VILLANUEVA ILUFI | G16: Sistema de gestión de postulantes de la Universidad Diego Portales a becas del Ministerio de Educación | H16: 2015 | I16: Creative Commons AtribuciónNoComercial | J16: AUTORIZADO | K16: SI | L16: =IF(K16 = "SI", EXTRA!$C$3, EXTRA!$C$4) | M16: En la Universidad Diego Portales no se informan correctamente los antecedentes académicos de aquellos alumnos que postulan a becas del Ministerio de Educación, provocando con ello, la pérdida del respaldo económico, que debe asumir la Universidad. La solución comprende el modelamiento del proceso de respaldo de postulantes UDP, para posteriormente diseñar y desarrollar una plataforma Web que apoye estos procesos, lo que permite informar oportuna y correctamente los postulantes en la plataforma Web que dispone el MINEDUC. La solución se divide en módulos que apoyan los procesos de alumnos nuevos que ingresan por primera vez a un programa de estudios dentro de la Universidad, alumnos antiguos en la UDP que nunca han postulado a una beca ministerial además de aquellos alumnos que renuevan su beneficio anualmente, finalmente postulantes que son beneficiados con la beca de reparación Valech, ya sean, titulares, hijos o nietos. En la etapa de diseño, a través de reuniones con el usuario final, se formalizaron los requerimientos funcionales; a partir de éstos, se construyeron casos de uso y el modelo de interfaz de usuario, lo anterior es fundamental para determinar como el usuario final interactúa con la plataforma Web, además es la hoja de ruta para el desarrollo. Para comprobar la correlación entre estos elementos se elaboraron matrices de trazabilidad. Para asegurar persistencia y consistencia de los datos se construyó una base de datos que permite almacenar y acceder a éstos de forma rápida y estructurada. Para el desarrollo del sistema se utiliza el patrón de diseño modelo vista controlador (MVC), este patrón permite separar la interfaz de usuario (vista), de la lógica de negocios (controlador) y la base de datos (modelo) De acuerdo a las pruebas realizadas se pudo determinar que la aplicación funciona para la totalidad de los casos de prueba ejecutados. | N16: https://usach.primo.exlibrisgroup.com/discovery/delivery/56USACH_INST:REPOSITORIO/1226610300006116 | O16: UNIVERSIDAD DE SANTIAGO DE CHILE | P16: DEPARTAMENTO DE INGENIERÍA INFORMÁTICA | Q16: (7) Computer Science | R16: (15) Software Engineering | S16: alumnos, usuario, datos, modelo, permite, plataforma, postulantes, universidad, web, además | T16: (3) Software Design
A17: LEONARDO ALEXIS CABRERA LOBOS | B17: INGENIERÍA CIVIL EN INFORMÁTICA | C17: DIURNA | E17: ROSA MUÑOZ CALANCHIE | G17: Desarrollo de un Framework para la construcción de objetos de aprendizaje | H17: 2015 | I17: Creative Commons AtribuciónNoComercial | J17: AUTORIZADO | K17: SI | L17: =IF(K17 = "SI", EXTRA!$C$3, EXTRA!$C$4) | M17: El presente trabajo documenta el proceso de desarrollo de un framework para apoyar la construcción de objetos de aprendizaje. Dicho framework se implementó basándose en la metodología CPIS para la construcción de los mismos. La motivación de este trabajo surge a partir de la detección de la necesidad de normalizar los procesos de software asociados a la construcción de objetos de aprendizaje y, al mismo tiempo, las bases de código que los constituyen. Para su generación, se hizo una revisión de los conceptos que caracterizan los objetos de aprendizaje y se estudió en profundidad la metodología antes mencionada. Luego, se aplicaron métodos de ingeniería de software para determinar los requerimientos de usuario y software. Posteriormente se realizó una caracterización técnica del framework en cada aspecto del mismo. Finalmente, se implementó el software de acuerdo a las especificaciones documentadas y las tecnologías escogidas. Para su validación, se construyó un objeto de aprendizaje utilizando tanto la metodología CPIS como el framework. Al mismo tiempo, se aprovecharon las cualidades que el framework provee para optimizar procesos dentro de dicha metodología. El producto resultante es un software que puede ser utilizado y reutilizado en la construcción de objetos de aprendizaje futuros. | N17: https://usach.primo.exlibrisgroup.com/discovery/delivery/56USACH_INST:REPOSITORIO/1226636390006116 | O17: UNIVERSIDAD DE SANTIAGO DE CHILE | P17: DEPARTAMENTO DE INGENIERÍA INFORMÁTICA | Q17: (7) Computer Science | R17: (15) Software Engineering | S17: aprendizaje, framework, software, construcción, metodología, objetos, mismo, cpis, implementó, procesos | T17: (3) Software Design
A18: GABRIEL ANTONIO SALAZAR MORENO | B18: INGENIERÍA CIVIL EN INFORMÁTICA | C18: DIURNA | E18: ROSA MUÑOZ CALANCHIE | G18: Reingeniería de objetos de aprendizaje para ser usados ​​en múltiples dispositivos | H18: 2015 | I18: Creative Commons AtribuciónNoComercialCompartirIgual | J18: AUTORIZADO | K18: SI | L18: =IF(K18 = "SI", EXTRA!$C$3, EXTRA!$C$4) | M18: El presente trabajo de titulación muestra el proceso del cambio de diseño de material pedagógico de apoyo en formato de Objetos de Aprendizaje (OAs), para que éstos puedan ser usados en múltiples dispositivos como computadores de escritorio y dispositivos móviles como tablets y smartphones, independientemente del hardware y del software con el cual funcionen estos dispositivos. Debido a que los Objetos de Aprendizaje usados en los cursos de “Redes de Comunicación” y “Criptografía y Protocolos de Seguridad” del Departamento de Ingeniería Informática de la Universidad de Santiago están disponibles en formato Flash, y sumado a que este formato ha quedado obsoleto y las actuales plataformas están migrando hacia nuevos estándares de contenido Web, se hace necesario transformar estos OAs para que los alumnos de estos cursos u otros similares puedan hacer uso de ellos en los dispositivos que usan con frecuencia, y de esta forma recuperar los OAs para apoyar el proceso de enseñanza en estas asignaturas. Para el rediseño de estos OAs se realizó un breve análisis a distintos trabajos de titulación en que se desarrollaron los mismos y luego se utilizó una metodología que consta de cuatro etapas: análisis, diseño, construcción y pruebas. El resultado de estas fases son nuevos OAs que pueden ser usados independientemente de la plataforma que el alumno decida usar, usando estándares actuales como HTML5. El desarrollo de los nuevos OAs incorpora las recomendaciones sobre usabilidad y funcionalidades que los expertos en estos temas recomendaron a los autores de los Objetos de Aprendizaje originales, particularmente en las actividades y evaluaciones que los nuevos Objetos de Aprendizaje ofrecen a los alumnos. | N18: https://usach.primo.exlibrisgroup.com/discovery/delivery/56USACH_INST:REPOSITORIO/1226546170006116 | O18: UNIVERSIDAD DE SANTIAGO DE CHILE | P18: DEPARTAMENTO DE INGENIERÍA INFORMÁTICA | Q18: (7) Computer Science | R18: (14) Software Development Fundamentals | S18: oas, aprendizaje, dispositivos, nuevos, objetos, formato, usados, actuales, alumnos, análisis | T18: (3) Software Design
A19: FELIPE ANTONIO IRIBARREN VIERTEL | B19: INGENIERÍA CIVIL EN INFORMÁTICA | C19: DIURNA | E19: ROSA MUÑOZ CALANCHIE | G19: Desarrollo de un objetivo de aprendizaje para apoyar el estudio de Android | H19: 2015 | I19: Creative Commons AtribuciónNoComercial | J19: AUTORIZADO | K19: SI | L19: =IF(K19 = "SI", EXTRA!$C$3, EXTRA!$C$4) | M19: Con el constante avance de las tecnologías y la cada vez más integración de ésta en la vida cotidiana de las personas, los Objetos de Aprendizaje cada día toman mayor relevancia, puesto que ellos presentan los contenidos de manera didáctica e interactiva que resulta más interesante para las personas. Sin ir más lejos, los mismos estudiantes universitarios actualmente están altamente familiarizados con las tecnologías, lo cual permite a través de imágenes y animaciones entregar los conceptos básicos de la programación en Android, que en la actualidad, es uno de los principales sistemas operativos para dispositivos móviles. Para lograrlo, se desarrolla un Objeto de Aprendizaje orientado a los estilos de aprendizaje predominantes en el grupo de usuarios del mismo y utilizando la metodología CPIS y la herramienta Adobe Edge Animate CC 2014. Finalmente, el Objeto de Aprendizaje desarrollado fue validado en tres aspectos: evaluación del experto, cumplimiento de los requerimientos y evaluación de los usuarios objetivo. El resultado principal de este trabajo es un Objeto de Aprendizaje en HTML5 que aborda los conceptos básicos de la programación en Android junto con un documento que presenta el marco teórico referente al tema y las consideraciones tomadas para su desarrollo. Con esto, se permite que cualquier interesado en el tema pueda estudiar los conceptos básicos que le permitan sentar cimientos conceptuales sólidos para afrontar la codificación misma de una aplicación Android. | N19: https://usach.primo.exlibrisgroup.com/discovery/delivery/56USACH_INST:REPOSITORIO/1226596570006116 | O19: UNIVERSIDAD DE SANTIAGO DE CHILE | P19: DEPARTAMENTO DE INGENIERÍA INFORMÁTICA | Q19: (7) Computer Science | R19: (14) Software Development Fundamentals | S19: aprendizaje, android, básicos, conceptos, objeto, cada, evaluación, permite, personas, programación | T19: (3) Software Design
A20: MAURICIO LEONEL CARÚS FLORES | B20: INGENIERÍA CIVIL EN INFORMÁTICA | C20: DIURNA | E20: ROSA MUÑOZ CALANCHIE | G20: Generador de objetos de aprendizaje basados en metodología CPIS | H20: 2015 | I20: Creative Commons AtribuciónNoComercial | J20: AUTORIZADO | K20: SI | L20: =IF(K20 = "SI", EXTRA!$C$3, EXTRA!$C$4) | M20: Con el objeto de apoyar a los académicos de la Universidad Academia de Humanismo Cristiano (UAHC) en la entrega de material de apoyo para las diferentes materias que enseñan en las carreras que imparte la Universidad, es que se considera la aplicación de objetos de aprendizaje. No obstante, el desconocimiento de los académicos de estas herramientas, sus características, requerimientos y actualización en el tiempo son factores que ven como trabas a la hora de aplicar este tipo de herramientas en su uso cotidiano como apoyo a la enseñanza. Para solucionar esta problemática es que se propone la creación de una aplicación que apoye a los docentes en el proceso de creación, evaluación y mantención de objetos de aprendizaje, basada en una metodología de creación de OA originada en las dependencias de la Universidad de Santiago de Chile, denominada metodología CPIS. Por otro lado, para llevar a cabo la realización del sistema propuesto, se utiliza una metodología de desarrollo de aplicaciones (OMT++ Simplificado), que permite un proceso estructurado e iterativo de desarrollo de sistemas computacionales, la cual detalla cada una de sus etapas con artefactos que apoyan la toma de requerimientos, el análisis, el diseño y la programación del futuro sistema. El resultado principal de este trabajo es la aplicación “CPIS Manager”, que es un sistema computacional que permite guiar al usuario en la creación de objetos de aprendizaje utilizando la metodología CPIS, de modo que los académicos de la UAHC puedan ser capaces de crear sus propios OA, evaluarlos y modificarlos en el tiempo. | N20: https://usach.primo.exlibrisgroup.com/discovery/delivery/56USACH_INST:REPOSITORIO/1226565710006116 | O20: UNIVERSIDAD DE SANTIAGO DE CHILE | P20: DEPARTAMENTO DE INGENIERÍA INFORMÁTICA | Q20: (7) Computer Science | R20: (14) Software Development Fundamentals | S20: creación, metodología, académicos, aplicación, aprendizaje, cpis, objetos, sistema, universidad, apoyo | T20: (3) Software Design
A21: JUAN PABLO LEÓN ARCE | B21: INGENIERÍA CIVIL EN INFORMÁTICA | C21: DIURNA | E21: ROSA MUÑOZ CALANCHIE | G21: Objeto de aprendizaje para apoyar el aprendizaje de la herramienta OMNET++ | H21: 2015 | I21: Creative Commons AtribuciónNoComercialCompartirIgual | J21: AUTORIZADO | K21: SI | L21: =IF(K21 = "SI", EXTRA!$C$3, EXTRA!$C$4) | M21: En el presente trabajo de titulación se desarrolla un Objeto de aprendizaje (OA) cuyo propósito es aportar en la disminución de los tiempos de aprendizaje de la herramienta de simulación Omnet ++ utilizada por los estudiantes del curso de Redes de Comunicación de la Universidad de Santiago de Chile. El desarrollo del trabajo se realizó bajo la método ágil CPIS la cual está enfocada en la creación de OAs mediante la aplicación de las fases de definición, selección de material, diseño, construcción y evaluación de calidad, donde la última etapa fue realizada utilizando el método propuesto por Álvaro Salas el cual consiste en que tres expertos realicen la evaluación de calidad del objeto revisando aspectos pedagógicos, técnicos y de usabilidad. Se logró la creación de 3 OAs. El primero de ellos es del tipo conceptual cuyo contenido se enfoca en describir el uso de la herramienta Omnet y de los lenguajes de programación NED y C++ asociados a éste. El segundo es del tipo procedimental donde se insta a los alumnos a realizar su primera simulación en Omnet++. El último de ellos es del tipo procedimental donde se explica cómo instalar y configurar la herramienta Omnet++. La prueba de uso de los objetos fue realizada por dos grupos de usuarios los cuales utilizaron y realizaron las actividades propuestas en éstos. El primer grupo se compuso por alumnos del curso de Redes de Comunicación en una de las Salas del Departamento de Informática de la Universidad de Santiago de Chile, mientras que el segundo grupo fue conformado por voluntarios desde sus propios hogares. Los datos de la prueba de uso de los objetos y de calidad permiten concluir que estos OAs cumplen su función de enseñar los conceptos básicos de un modelo Omnet++ y de guiar al usuario a realizar su primera simulación en Omnet. | N21: https://usach.primo.exlibrisgroup.com/discovery/delivery/56USACH_INST:REPOSITORIO/1226493000006116 | O21: UNIVERSIDAD DE SANTIAGO DE CHILE | P21: DEPARTAMENTO DE INGENIERÍA INFORMÁTICA | Q21: (7) Computer Science | R21: (14) Software Development Fundamentals | S21: omnet, calidad, herramienta, oas, simulación, tipo, uso, alumnos, aprendizaje, chile | T21: (1) Software Requirements
A22: MARCELO ANTONIO MADARIAGA MORENO | B22: INGENIERÍA CIVIL EN INFORMÁTICA | C22: DIURNA | E22: SERGIO VELASTÍN CARROZA | G22: Comparación de aplicaciones para la detección de vehículos detenidos en sectores prohibidos del tráfico urbano | H22: 2015 | I22: Creative Commons AtribuciónNoComercial | J22: AUTORIZADO | K22: SI | L22: =IF(K22 = "SI", EXTRA!$C$3, EXTRA!$C$4) | M22: En el presente trabajo de titulación se pretende solucionar la detección de vehículos detenidos en sectores prohibidos del tráfico urbano, teniendo como iniciativa, el proyecto del Ministerio de Transporte que hace referencia a la detección de vehículos que se detengan en las intersecciones de avenidas, donde existe la ley del tránsito “no bloquear el cruce”. La solución propuesta para esta problemática es evaluar sistemas comerciales que resuelvan esta problemática mediante visión por computador, determinando qué sistema tiene mayor desempeño en la detección de vehículos en tiempo real. Los sistemas comerciales participantes en este trabajo son Ipsotek y Acic, líderes mundiales en soluciones de esta índole. Para poder determinar qué sistema comercial obtiene un mayor desempeño en la video analítica, es construida una base de datos de video en conjunto con Centro Estratégico de Fiscalización, CEF, con el fin de realizar una evaluación de desempeño a los sistemas comerciales antes mencionados. La evaluación de desempeño de los sistemas comerciales se llevó a cabo en base a las siguientes métricas: tales como precision, recall y F1-Measure. Un sistema comercial debe cumplir criterios de aceptación, los cuales fueron definidos en base a la documentación de i-Lids Dataset (CAST and CPNI, 2011) y el Centro Estratégico de Fiscalización. Se establece que los sistemas comerciales deben tener un score de 0.7 en la métrica de evaluación F1-Measure. Los resultados obtenidos en base a la configuración y evaluación de desempeño de los sistemas comerciales, fueron favorables para el sistema comercial Acic Video Analitycs, con un score en la métrica F1-Measure de 0.4. | N22: https://usach.primo.exlibrisgroup.com/discovery/delivery/56USACH_INST:REPOSITORIO/1226610110006116 | O22: UNIVERSIDAD DE SANTIAGO DE CHILE | P22: DEPARTAMENTO DE INGENIERÍA INFORMÁTICA | Q22: (7) Computer Science | R22: (3) Artificial Intelligence | S22: comerciales, sistemas, desempeño, base, evaluación, sistema, comercial, detección, f, measure | T22: (5) Software Testing
A23: MIGUEL ANGEL MALDONADO ALGÜERNA | B23: INGENIERÍA CIVIL EN INFORMÁTICA | C23: DIURNA | E23: ROSA MUÑOZ CALANCHIE | G23: Sistema de cálculo de reservas : técnicas para seguros generales | H23: 2015 | I23: SIN LICENCIA | J23: SIN AUTORIZACIÓN | K23: SI | L23: =IF(K23 = "SI", EXTRA!$C$3, EXTRA!$C$4) | M23: Los constantes cambios tecnológicos y normativos a los que están expuestas las grandes empresas, llevan a que estás inviertan grandes cantidades de dinero en procesos de desarrollo y mantención de sus sistemas Es así como en el presente trabajo se muestra una necesidad en la Compañía de Seguros Consorcio, necesidad que nace desde la obsolescencia de los procesos y tecnologías. Siendo apalancada por la gran cantidad de problemas y elementos de riesgo que conlleva el mantenerla sin cambios. El problema que se presenta, consiste en la definición e implementación (interna y externa) de un nuevo sistema para el Cálculo de las Reservas Técnicas para Seguros Generales. Proceso que se llevó por cerca de dos años de forma poco eficiente y riesgosa. La solución, considera tanto los aspectos funcionales como no funcionales requeridos en Consorcio. Es por ello que se buscaron las siguientes características a la hora de la implementación: proceso eficiente, que controle errores, que sea auditable y que sea centralizado. El desarrollo se separa en dos vías, una ejecutada por un proveedor externo a Consorcio y otra por el área tecnológica de la compañía. Es por lo anterior, que en el documento se hace énfasis al desarrollo del proceso de carga de datos de entrada, que es la parte desarrollada por Consorcio. Una vez construido el sistema, se obtuvieron y compararon los resultados con el proceso anterior, llegando a ver una notable mejora en los tiempos de procesamiento de los cálculos. Además de, una notable mejora en la experiencia de usuario. Llegando a un sistema que cumple con la normativa interna y externa, que realiza sus procesos de forma rápida y confiable, y que permite una mayor independencia de los usuarios finales. | N23: https://usach.primo.exlibrisgroup.com/discovery/delivery/56USACH_INST:REPOSITORIO/1241018800006116 | O23: UNIVERSIDAD DE SANTIAGO DE CHILE | P23: DEPARTAMENTO DE INGENIERÍA INFORMÁTICA | Q23: (4) Business, Management and Accounting | R23: (15) Software Engineering | S23: consorcio, proceso, desarrollo, procesos, sistema, anterior, cambios, compañía, dos, eficiente | T23: (3) Software Design
A24: GUSTAVO ALBERTO SALVO LARA | B24: INGENIERÍA CIVIL EN INFORMÁTICA | C24: DIURNA | E24: BRUNO JERARDINO WIESENBORN | G24: Una aplicación móvil desarrollada con lean UX para el apoyo a los postulantes en el examen teórico de conducción | H24: 2015 | I24: Creative Commons AtribuciónNoComercialSinDerivadas | J24: AUTORIZADO | K24: SI | L24: =IF(K24 = "SI", EXTRA!$C$3, EXTRA!$C$4) | M24: En el presente trabajo se muestra el proceso de desarrollo de una aplicación móvil para dispositivos con sistema operativo Android con el objetivo de apoyar a los postulantes del examen teórico de conducción para la obtención de licencias clase B y C. Se cuenta con la colaboración de la Ilustre Municipalidad de Cerrillos principalmente para establecer el contacto inicial con los postulantes de esa comuna y aclarar dudas sobre la normativa vigente del examen que se realiza. El trabajo constituye un proyecto interno de la Universidad y surge en base al alto porcentaje de reprobación que existe actualmente en el país en el examen teórico de conducción, luego de la nueva implementación a finales del año 2012. El desarrollo del proyecto fue guiado por la metodología Lean UX lo cual permitió generar valor rápidamente a los usuarios mediante la entrega continua de versiones del producto y comprobar los supuestos establecidos al inicio en relación a la problemática que se aborda y el comportamiento de los usuarios con el producto. Junto con la aplicación móvil el proyecto también considera el desarrollo de una plataforma web que permite administrar de forma liviana, sencilla y rápida el contenido que acceden los usuarios desde la aplicación. Actualmente la aplicación se encuentra disponible al público de manera gratuita en Play Store para las personas que poseen dispositivos móviles con sistema operativo Android desde su versión 4.0 en adelante, y desean poner a prueba sus conocimientos teóricos de conducción. | N24: https://usach.primo.exlibrisgroup.com/discovery/delivery/56USACH_INST:REPOSITORIO/1226463500006116 | O24: UNIVERSIDAD DE SANTIAGO DE CHILE | P24: DEPARTAMENTO DE INGENIERÍA INFORMÁTICA | Q24: (7) Computer Science | R24: (14) Software Development Fundamentals | S24: aplicación, conducción, desarrollo, examen, proyecto, usuarios, actualmente, android, dispositivos, móvil | T24: (3) Software Design
A25: NICOLÁS NAZRE NASER ABARZÚA | B25: INGENIERÍA CIVIL EN INFORMÁTICA | C25: DIURNA | E25: ROSA MUÑOZ CALANCHIE | G25: Objeto de aprendizaje para apoyar el proceso de lectura infantil | H25: 2015 | I25: Creative Commons AtribuciónNoComercial | J25: AUTORIZADO | K25: SI | L25: =IF(K25 = "SI", EXTRA!$C$3, EXTRA!$C$4) | M25: Actualmente, existe una gran falencia en comprensión lectora a nivel nacional, una de las maneras de dar solución a esta problemática, es mejorar el proceso desde su inicio, es decir, desde que se aprende a leer. El presente trabajo de titulación consiste en el desarrollo de un Objeto de Aprendizaje que apoye y ayude al proceso de aprendizaje-enseñanza de la lectura en niños de los primeros niveles básicos y pre-escolares. El Objeto de Aprendizaje desarrollado realiza una revisión completa de los contenidos necesarios para lograr ir paso a paso en el desarrollo de la habilidad lectora en los usuarios seleccionados, iniciando con la revisión de las letras, junto a sus grafemas y fonemas, partiendo por las vocales para pasar a las consonantes, pasando a la formación de silabas, palabras y primeras lecturas básicas. Se utilizó la metodología AODDEI para el desarrollo del Objeto de Aprendizaje propuesto. Además, se ocuparon los framework’s Twitter Bootstrap y Jquery, en conjunto de los lenguajes de programación HTML5, CSS3 y PHP. El Objeto de Aprendizaje se validó a través de pruebas de usabilidad, de requerimientos y siguiendo la opinión de expertos en cuanto a los temas metodológicos y conceptuales. Además, se probó con los alumnos de primero básico del colegio “Los Quillayes”, con un resultado exitoso desde el punto de vista pedagógico. Finalmente, es importante mencionar que con el trabajo realizado se obtiene el resultado esperado y se cumple con el desarrollo de una herramienta que apoye el proceso de aprendizaje de la lectura a nivel escolar básico. | N25: https://usach.primo.exlibrisgroup.com/discovery/delivery/56USACH_INST:REPOSITORIO/1226528570006116 | O25: UNIVERSIDAD DE SANTIAGO DE CHILE | P25: DEPARTAMENTO DE INGENIERÍA INFORMÁTICA | Q25: (7) Computer Science | R25: (14) Software Development Fundamentals | S25: aprendizaje, desarrollo, objeto, proceso, además, apoye, básico, lectora, lectura, nivel | T25: (3) Software Design
A26: MAXIMILIANO HERNÁNDEZ SAN MARTÍN | B26: INGENIERÍA CIVIL EN INFORMÁTICA | C26: DIURNA | E26: VÍCTOR PARADA DAZA | G26: Generación de algoritmos utilizando programación genética y coevolución con cambio de entorno para el problema de ordenamiento secuencial | H26: 2015 | I26: Creative Commons AtribuciónNoComercialCompartirIgual | J26: AUTORIZADO | K26: SI | L26: =IF(K26 = "SI", EXTRA!$C$3, EXTRA!$C$4) | M26: El presente trabajo de titulación tiene por objetivo probar un nuevo procedimiento a la hora de realizar evoluciones de algoritmos por medio de la Programación Genética. Para este ejercicio, se ha utilizado para la evaluación el Problema de Ordenamiento Secuencial, que pertenece a la categoría de problemas de optimización y que es una versión más compleja del tradicional problema del Vendedor Viajero. La nueva propuesta de procedimiento está basada en el modelo de dos islas de Chandra y Bali, y consiste en que a partir de dos poblaciones distintas que han evolucionado de forma independiente, se genere una nueva población con los mejores individuos de cada grupo, y se vuelvan a someter a una evolución, con el fin de ver si son capaces de obtener mejores resultados al tomar lo mejor de cada grupo. Para completar el procedimiento se ha utilizado la plataforma ECJ, que está diseñada para realizar procedimientos de Computación Evolutiva, lo cual implica que con la configuración adecuada, permite realizar trabajos con Programación Genética. Se han implementado los pasos que plantea la evolución natural, que son la selección, cruzamiento, mutación y reproducción, para simular este procedimiento y generar algoritmos de forma automatizada mediante el uso de ECJ. Los resultados obtenidos indican que el uso de la coevolución es una variable factible a la hora de buscar formas de mejorar los procesos evolutivos, ya que entrega resultados competitivos. Se ha logrado ver una mejora respecto al proceso tradicional en uno de los algoritmos propuestos. Y se estiman varias posibilidades que permitan mejorar estos resultados en trabajos futuros. | N26: https://usach.primo.exlibrisgroup.com/discovery/delivery/56USACH_INST:REPOSITORIO/1226466050006116 | O26: UNIVERSIDAD DE SANTIAGO DE CHILE | P26: DEPARTAMENTO DE INGENIERÍA INFORMÁTICA | Q26: (7) Computer Science | R26: (1) Algorithms and Complexity | S26: procedimiento, resultados, algoritmos, realizar, cada, dos, ecj, evolución, forma, genética | T26: (19) Research/Investigation
A27: CRISTIAN RICARDO CORNEJO LUENGO | B27: INGENIERÍA CIVIL EN INFORMÁTICA | C27: DIURNA | D27: MAGÍSTER EN INGENIERÍA INFORMÁTICA | E27: MARIO INOSTROZA-PONTA | G27: Algoritmo de agrupamiento para datos de expresión génica de RNA-Seg con la incorporación de anotaciones biológicas | H27: 2015 | I27: Atribución Creative Commons | J27: AUTORIZADO | K27: SI | L27: =IF(K27 = "SI", EXTRA!$C$3, EXTRA!$C$4) | M27: El desarrollo de nuevas tecnologías en el ámbito de la microbiología ha permitido el surgimiento de innovadoras técnicas para cuantificar el nivel de expresión de los genes dentro de una célula. Una de estas es RNA-Seq, la cual está reemplazando a los experimentos de microarreglos en esta a ́rea. Sin embargo, con el surgimiento de esta técnica es necesario un nuevo enfoque en el uso de métodos para el análisis de expresión o la generación de otros. Por otra parte, existen bases de datos que proveen información biológica complementaria sobre los genes, la cual puede ser utilizada como entrada para los métodos de análisis de expresión, y de esta manera, mejorar la coherencia biológica de sus resultados. Este trabajo propone un algoritmo de agrupamiento, basado en el algoritmo MST- kNN para agrupar genes utilizando información del nivel de expresión diferencial de estos, perfiles de expresión y anotaciones biológicas extraídas de Gene Ontology y STRING. La solución propuesta es comparada con el algoritmo MST-kNN, MST-kNN Bio y HTSCluster, usando datos de expresión de RNA-Seq para squamous cell carcinoma. Los resultados obtenidos muestran que el algoritmo propuesto logra agrupar genes con una coherencia biológica superior en hasta un 213% y niveles de coexpresión superiores en hasta un 180%, respecto a los algoritmos en comparación. Adema ́s de obtener particiones distintas con hasta un máximo de 0,16 de similaridad según el indice de Jaccard, utilizando la misma información de entrada que los algoritmos en comparación. De este modo se concluye que el uso de bases de datos, como Gene Ontology y STRING son un aporte para obtener grupos de genes con funcionalidades biológicas similares. Adema ́s el algoritmo propuesto probó ser una solución para el análisis de expresión de datos de RNA-Seq. | N27: https://usach.primo.exlibrisgroup.com/discovery/delivery/56USACH_INST:REPOSITORIO/1226606500006116 | O27: UNIVERSIDAD DE SANTIAGO DE CHILE | P27: DEPARTAMENTO DE INGENIERÍA INFORMÁTICA | Q27: (17) Materials Science | R27: (1) Algorithms and Complexity | S27: expresión, algoritmo, genes, datos, análisis, biológica, información, knn, mst, rna | T27: (19) Research/Investigation
A28: CARLOS ANDRÉS PÉREZ ROJAS | B28: INGENIERÍA CIVIL EN INFORMÁTICA | C28: DIURNA | D28: MAGÍSTER EN INGENIERÍA INFORMÁTICA | E28: GONZALO ACUÑA LEIVA | G28: Elaboración de modelos dinámicos para la predicción de variables de mantenimiento en minería utilizando herramientas de inteligencia computacional | H28: 2015 | I28: Atribución Creative Commons | J28: AUTORIZADO | K28: SI | L28: =IF(K28 = "SI", EXTRA!$C$3, EXTRA!$C$4) | M28: Dentro de la industria minera, las flotas de equipos pesados representan uno de los activos más importantes a nivel de producción. Para mantener estos equipos en condiciones óptimas de funcionamiento, se establecen programa de mantenciones para realizar un chequeo de toda la máquina. Sin embargo, estos programas no siempre son acertados y es común que se requieran realizar mantenciones imprevistas de alguno de los equipos de la flota, con lo cual se ve afectada la productividad de la flota completa. El presente documento muestra el trabajo realizado para diseñar, entrenar y validar un modelo de inteligencia computacional que tiene el fin de predecir la disponibilidad de una flota de ocho palas de la industria minera, para así poder establecer programas de mantención más precisos que beneficien directamente la productividad de estas máquinas, todo esto dentro del marco establecido en el Proyecto Fondef-IDeA CA13I10121. Para llevar a cabo el trabajo se propone utilizar un modelo NARX basado en redes neuronales y se plantean dos enfoques diferentes de entrenamiento, el primero consiste en entrenar un modelo diferente para cada pala y el segundo consiste en entrenar un único modelo para todas las palas. Cada enfoque presenta sus propias ventajas y desventajas. Finalmente se opta por utilizar el segundo enfoque, ya que se considera más adecuado para el área de trabajo. Los resultados obtenidos son alentadores, utilizando como entrenamiento los datos de una sola pala se logra predecir la disponibilidad del resto de las palas con un error promedio por debajo del 25%. Queda en evidencia entonces que es posible aplicar el modelo propuesto en la industria, ya que podría ayudar a generar programas de mantenciones más precisos, mejorando así la productividad de la flota de equipos. | N28: https://usach.primo.exlibrisgroup.com/discovery/delivery/56USACH_INST:REPOSITORIO/1226579450006116 | O28: UNIVERSIDAD DE SANTIAGO DE CHILE | P28: DEPARTAMENTO DE INGENIERÍA INFORMÁTICA | Q28: (7) Computer Science | R28: (3) Artificial Intelligence | S28: modelo, equipos, flota, entrenar, industria, mantenciones, palas, productividad, programas, trabajo | T28: (11) Software Engineering Models and Methods
A29: SEBASTIÁN SANTIAGO VIZCAY DERZA | B29: INGENIERÍA CIVIL EN INFORMÁTICA | C29: DIURNA | D29: MAGÍSTER EN INGENIERÍA INFORMÁTICA | E29: FERNANDO RANNOU FUENTES | G29: Simulación de Monte Carlo paralela para sistemas ferromagnéticos en un modelo de Heisenberg incluyendo interacciones dipolares | H29: 2015 | I29: Atribución Creative Commons | J29: AUTORIZADO | K29: SI | L29: =IF(K29 = "SI", EXTRA!$C$3, EXTRA!$C$4) | M29: En este trabajo de tesis se presentan diferentes técnicas de paralelismo aplicadas al modelo mecánico estadístico de Heisenberg con interacciones de largo alcance. Las técnicas utilizadas incluyen paralelismo en GPU, explotación de arquitecturas multicore con OpenMP y vectorización a través de SIMD. Dentro de los modelos de spins, el modelo de Heisenberg se trata con menos frecuencia que otros modelos como el modelo de Ising y el modelo de spin glass, además que rara vez se incluyen interacciones de largo alcance en el Hamiltoniano utilizado para describir al sistema. Dentro del total de pruebas realizadas, se logra disminuir el tiempo de ejecución de las simulaciones Monte Carlo reportando un valor de speedup de 30 al utilizar OpenMP en conjunto con SIMD. | N29: https://usach.primo.exlibrisgroup.com/discovery/delivery/56USACH_INST:REPOSITORIO/1226576920006116 | O29: UNIVERSIDAD DE SANTIAGO DE CHILE | P29: DEPARTAMENTO DE INGENIERÍA INFORMÁTICA | Q29: (7) Computer Science | R29: (11) Parallel and Distributed Computing | S29: modelo, alcance, dentro, heisenberg, incluyen, interacciones, largo, modelos, openmp, paralelismo | T29: (19) Research/Investigation
A30: MARIO LUIS LÓPEZ LANDES | B30: INGENIERÍA CIVIL EN INFORMÁTICA | C30: DIURNA | E30: BRUNO JERARDINO WIESENBORN | G30: Una aplicación móvil que apoya la realización de la metodología de sistema blandos de Peter Checkland | H30: 2015 | I30: Atribución Creative Commons | J30: AUTORIZADO | K30: SI | L30: =IF(K30 = "SI", EXTRA!$C$3, EXTRA!$C$4) | M30: El presente trabajo de titulación consiste en la construcción de una aplicación móvil que apoye la realización de la Metodología de Sistemas Blandos de Peter Checkland. Su desarrollo se encuentra precedido por la construcción de una aplicación Web llamada Soft Systems Manager. La aplicación móvil integra sus funcionalidades directamente sobre esta, conformando en conjunto un sistema capaz de proveer servicios sobre múltiples dispositivos. La aplicación móvil logra cubrir los primeros tres estadios de la metodología de sistemas blandos y almacena su información directamente en la nube, donde la comparte con la aplicación Web. Ambos sistemas se encuentran integrados y desplegados sobre el motor Google App Engine. Para llevar a cabo el desarrollo del software, se trabajó en base a la metodología AUP (Agile Unified Process). Para la construcción de la aplicación se hizo uso de la tecnología open source Apache Cordova y el framework AngularJS. La base de datos se encuentra soportada por la tecnología Google Cloud Datastore, mientras que el material multimedia capturado por los usuarios es almacenado en Google Cloud Storage. La aplicación logró ser desplegada sobre los sistemas Android (4.0+) y iOS (7.1+), presentando las mismas funcionalidades en ambos sistemas operativos. Sin embargo, no estuvo dentro del alcance de este trabajo realizar el trabajo de publicar la aplicación en los proveedores oficiales (Google Play y AppStore); sólo se investigó sobre este proceso. La aplicación fue puesta a prueba bajo pruebas de aceptación, las cuales permitieron determinar que la aplicación cumple los requisitos levantados. Además, se han documentado las capas fundamentales del software, el cual además, se encuentra publicado en la plataforma GitHub. | N30: https://usach.primo.exlibrisgroup.com/discovery/delivery/56USACH_INST:REPOSITORIO/1226522530006116 | O30: UNIVERSIDAD DE SANTIAGO DE CHILE | P30: DEPARTAMENTO DE INGENIERÍA INFORMÁTICA | Q30: (7) Computer Science | R30: (16) Specialized Platform Development | S30: aplicación, sistemas, google, construcción, encuentra, metodología, móvil, trabajo, además, ambos | T30: (3) Software Design
A31: CAMILA FERNANDA TORRES VILLANUEVA | B31: INGENIERÍA CIVIL EN INFORMÁTICA | C31: DIURNA | E31: MÓNICA VILLANUEVA ILUFI | G31: Algoritmos paralelos para la generación de los conjuntos independientes maximales de un grafo camino sin cuerdas y de un grafo caterpillar | H31: 2015 | I31: Creative Commons AtribuciónNoComercialCompartirIgual | J31: AUTORIZADO | K31: SI | L31: =IF(K31 = "SI", EXTRA!$C$3, EXTRA!$C$4) | M31: Un grafo camino sin cuerdas se define por una secuencia de n vértices v1, v2,...,vn tal que (vi, vi+1) es una arista para 1 ≤ i ≤ n-1 y además no existe ninguna arista que una dos de sus vértices no consecutivos. Un grafo caterpillar es un árbol en donde al remover todos los vértices hojas resulta en un grafo camino. En este trabajo se enumeran todos los conjuntos independientes maximales (C.I.M) de un grafo camino sin cuerdas (Pn) y de un grafo caterpillar C(Pn). En el desarrollo de la memoria se presentan los siguientes algoritmos: un algoritmo secuencial iterativo que genera toda la familia de C.I.M. de un grafo camino sin cuerdas, dos algoritmos paralelos para la generación de toda la familia de C.I.M. de un grafo camino sin cuerdas y por último dos algoritmos paralelos para la generación de todos los conjuntos independientes maximales de un grafo caterpillar. Para el desarrollo del trabajo se utiliza el método científico, compuesto por las siguientes etapas: observación del fenómeno, formulación de la hipótesis, diseño experimental, análisis de resultados y conclusiones. En la etapa de análisis de resultados se comparan los algoritmos creados, en términos de tiempo y memoria utilizada, con el algoritmo de Tsukiyama et.al. (1977) y con el algoritmo MISPATH (Villanueva, 1993), en el caso de un grafo Pn, y el algoritmo MISCAT (Villanueva & Ortiz, 2012) para grafos C(Pn). En las comparaciones se observa que la memoria utilizada por los algoritmos paralelos ya sea para los grafos camino sin cuerdas y caterpillar, es mínima (entre 1-5 MB), a diferencia del algoritmo de Tsukiyama et. al. que utiliza una gran cantidad de memoria (sobre 32 GB para P70). En cuanto al tiempo utilizado, el algoritmo paralelo para grafos camino sin cuerdas obtuvo mejores resultados que el algoritmo de Tsukiyama et. al., no así con el algoritmo caterpillar, en donde los tiempos fueron similares. | N31: https://usach.primo.exlibrisgroup.com/discovery/delivery/56USACH_INST:REPOSITORIO/1226589340006116 | O31: UNIVERSIDAD DE SANTIAGO DE CHILE | P31: DEPARTAMENTO DE INGENIERÍA INFORMÁTICA | Q31: (7) Computer Science | R31: (1) Algorithms and Complexity | S31: grafo, algoritmo, camino, cuerdas, algoritmos, c, caterpillar, i, memoria, pn | T31: (19) Research/Investigation
A32: YHANN CARLOS JARA GODOY | B32: INGENIERÍA CIVIL EN INFORMÁTICA | C32: DIURNA | E32: ARTURO ÁLVAREZ CEA | G32: Software para planificación de vuelo fotogramétrico de UAV en terrenos de complejos | H32: 2015 | I32: SIN LICENCIA | J32: SIN AUTORIZACIÓN | K32: SI | L32: =IF(K32 = "SI", EXTRA!$C$3, EXTRA!$C$4) | M32: El presente trabajo de titulación consiste en el diseño, implementación y validación de un sistema que facilite la etapa de planificación de vuelo para trabajos de fotogrametría UAV. El resultado de un vuelo fotogramétrico es un set de fotogramas que son procesadas, para obtener una ortofotografía con una escala en donde es posible medir distancias según los pixeles, es por esto que la planificación de vuelo debe considerar principalmente dos factores: mantener homogéneo el GSD de las fotografías obtenidas y priorizar la seguridad del UAV para garantizar su integridad. La estrategia principal para lograr dicho propósito es dividir el lugar a volar en subáreas de tal forma que se logre una altura de vuelo uniforme y distante del suelo. El proyecto es llevado a cabo utilizando la metodología ágil conocida como AUP, la cual se divide en 4 fases: concepción, elaboración, construcción y transición. Durante estas fases se lleva a cabo las distintas actividades necesarias para la creación del sistema entre las cuales están: la obtención de los requerimientos junto a la ayuda de la empresa que propuso este proyecto llamada SISAR Ltda, el diseño de la arquitectura de la aplicación en donde destaca el uso de la estación de control terrestre Mission Planner utilizada como base para desarrollar el sistema, la construcción del sistema propiamente tal utilizando Visual Studio y el framework .NET en que se encuentra construido Mission Planner, y la ejecución de pruebas en entornos simulados y reales para validar que el sistema cumple con los estándares de seguridad y calidad requeridos. Una vez finalizado el proyecto se cumple con el objetivo principal de obtener un sistema capaz de facilitar la labor de planificación de vuelo fotogramétrico del UAV respetando en lo posible la homogeneidad de las imágenes y dentro de los márgenes de seguridad de vuelo. | N32: https://usach.primo.exlibrisgroup.com/discovery/delivery/56USACH_INST:REPOSITORIO/1241018860006116 | O32: UNIVERSIDAD DE SANTIAGO DE CHILE | P32: DEPARTAMENTO DE INGENIERÍA INFORMÁTICA | Q32: (7) Computer Science | R32: (14) Software Development Fundamentals | S32: sistema, vuelo, planificación, proyecto, seguridad, uav, cabo, construcción, cumple, diseño | T32: (3) Software Design
A33: FABIÁN ANDRÉS ARISMENDI FERRADA | B33: INGENIERÍA CIVIL EN INFORMÁTICA | C33: DIURNA | D33: MAGÍSTER EN INGENIERÍA INFORMÁTICA | E33: CAROLINA BONACIC CASTRO | G33: Método de modelamiento dinámico de tópicos para la red social Twitter | H33: 2015 | I33: Atribución Creative Commons | J33: AUTORIZADO | K33: SI | L33: =IF(K33 = "SI", EXTRA!$C$3, EXTRA!$C$4) | M33: En la actualidad, existe una tendencia a digitalizar la comunicación abierta o no dirigida, en la cual las personas externalizan sus opiniones sobre temas o situaciones actuales de su entorno cotidiano. Debido a este presente y futuro escenario social, surge la necesidad de realizar análisis en los medios de comunicación digital, también conocidos como redes sociales digitales, lo que permite descubrir tendencias, problemas y situaciones comunes de personas no relacionadas directamente con ellos. Por otro lado, la informática proporciona herramientas que permiten realizar estudios profundos y aportes concretos a los estudios sociales del comportamiento humano, desde análisis de sentimientos e intenciones de compra hasta identificación de temas temporales mediante métodos de clasificación y categorización de texto. Una forma de entender la tendencia de las personas a clasificar los temas comunes en intervalos de tiempo definidos es mediante as temáticas, también conocidas como tópicos Latent Dirichlet Allocation(LDA) es la técnica más utilizada para crear dichos conjuntos o modelos de tópicos, y se trata de un método probabilístico de distribución a priori que permite realizar la categorización y clasificación de un conjunto de documentos de forma aleatoria. Sin embargo, existe un problema a abordar: la temporalidad de los datos de entrada y la validez de los resultados de salida entregados en un intervalo de tiempo. Se debe verificar la posibilidad de obtener resultados históricos y parciales con resultados equivalentes en el tiempo, para así poder aumentar la información que proporcional a técnica LDA a través de las diferencias y semejanzas de cada modelo en el tiempo. La solución propuesta es la creación de una función de prioridad de tópicos que permita realizar modelos de tópicos aplicados a secciones de tiempo secuenciales y ordenar los resultados acumulados. Una vez logrado lo anterior, se podrá realizar una comparación con un modelo de tópicos histórico que utilice diferentes métricas tales como las frecuencias y relaciones entre documentos, tópicos y palabras, lo que permitirá realizar una predicción del comportamiento de los tópicos en el tiempo y conocer su relevancia. Los resultados obtenidos en la investigación fueron: Un método de modelamiento dinámico de tópicos orientado al preprocesamiento de los datos obtenidos de las redes sociales y un análisis de características influyentes en cada tópico enfocado a la comparación y ponderación al utilizar diferentes subconjuntos de documentos para la generación de modelos de tópicos, permitiendo una categorización de los tópicos en base a sus características. | N33: https://usach.primo.exlibrisgroup.com/discovery/delivery/56USACH_INST:REPOSITORIO/1226450620006116 | O33: UNIVERSIDAD DE SANTIAGO DE CHILE | P33: DEPARTAMENTO DE INGENIERÍA INFORMÁTICA | Q33: (7) Computer Science | R33: (3) Artificial Intelligence | S33: tópicos, realizar, tiempo, resultados, análisis, categorización, documentos, modelos, personas, sociales | T33: (19) Research/Investigation
A34: ALEX PATRICIO AHUMADA AHUMADA | B34: INGENIERÍA CIVIL EN INFORMÁTICA | C34: DIURNA | E34: MÓNICA VILLANUEVA ILUFI | G34: Sistema de apoyo a la formulación de proyectos concursables del Departamento de Ingeniería Informática de la Universidad de Santiago de Chile | H34: 2015 | I34: Creative Commons AtribuciónNoComercial | J34: AUTORIZADO | K34: SI | L34: =IF(K34 = "SI", EXTRA!$C$3, EXTRA!$C$4) | M34: El presente informe da a conocer el Sistema de Apoyo a la Formulación de Proyectos Concursables del Departamento de Ingeniería Informática de la Universidad de Santiago de Chile (DIINF), propuesto como trabajo para la obtención del título de Ingeniero Civil en Informática. En la actualidad, el DIINF tiene aspectos que se pueden mejorar en cuanto a la postulación a proyectos concursables por parte de los académicos del Departamento. El proceso de gestión de proyectos concursables considera diversas etapas, las cuales corresponden - a grandes rasgos - la generación de la idea, la formulación de la propuesta, la postulación a concursos, realización del proyecto, seguimiento y cierre. Para esto se ha construido un sistema de apoyo a la formulación de proyectos para concursos internos, como los convocados por Dicyt, y para concursos externos, como por ejemplo, los llamados por Conicyt. El trabajo es realizado utilizando la metodología de desarrollo AUP, la cual se compone de cuatro fases. La primera de ellas es la fase de iniciación del proyecto. La segunda etapa considera la elaboración, en la cual se establecen las bases para la construcción del sistema. En la fase de construcción se desarrolla el sistema, según lo considerado en la fase de elaboración, en donde se pueden observar las distintas interfaces con las cuales interactúa el usuario, para finalmente dar paso a la fase de transición, en donde se realizan 30 casos de prueba, guiados por los casos de uso, para verificar el correcto funcionamiento del sistema implementado. Se espera que a futuro el trabajo presentado sea unificado a otros sistemas realizados por memoristas de la profesora Mónica Villanueva Ilufi, tomando como base el trabajo de título de Luciano Hidalgo “Reingeniería de procesos de docencia del Departamento de Ingeniería Informática de la Universidad de Santiago de Chile”. | N34: https://usach.primo.exlibrisgroup.com/discovery/delivery/56USACH_INST:REPOSITORIO/1226533800006116 | O34: UNIVERSIDAD DE SANTIAGO DE CHILE | P34: DEPARTAMENTO DE INGENIERÍA INFORMÁTICA | Q34: (7) Computer Science | R34: (15) Software Engineering | S34: sistema, fase, proyectos, trabajo, concursables, concursos, departamento, formulación, informática, apoyo | T34: (3) Software Design
A35: SEBASTIÁN ALEJANDRO ARAYA MORALES | B35: INGENIERÍA CIVIL EN INFORMÁTICA | C35: DIURNA | E35: CAROLINA BONACIC CASTRO | G35: Software de ejercicios de estimulación y evaluación motora para pacientes con Parkinson | H35: 2015 | I35: Creative Commons AtribuciónNoComercialCompartirIgual | J35: AUTORIZADO | K35: SI | L35: =IF(K35 = "SI", EXTRA!$C$3, EXTRA!$C$4) | M35: Este proyecto se basa en dar una solución a ciertos problemas que surgen en el seguimiento y monitorización de pacientes que padecen la enfermedad de Parkinson. Dicha solución se plasma en el desarrollo de un sistema de medida inercial portable y de bajo costo, que se basa en la utilización de ciertos sensores de dispositivos móviles y en el desarrollo de un software móvil utilizando tecnologías actuales que permiten la creación de aplicaciones móviles híbridas multiplataforma. Por lo tanto, con esta solución se pretende brindar una ayuda a especialistas del área en la detección de la actividad psicomotora en pacientes que padecen la enfermedad de Parkinson, mediante datos cuantitativos otorgados por los sensores del dispositivo móvil, los cuales se traducen en estadísticas y registros de evolución de la enfermedad. Además, se busca aportar una autonomía a las personas que padecen dicha enfermedad, otorgando un mayor bienestar tanto para el individuo como para su familia. La primera parte de este documento se centra en definir qué es la enfermedad de Parkinson, cómo se puede detectar y cuáles son las necesidades tanto de las personas que padecen esta enfermedad como de los especialistas quienes deben llevar un seguimiento y evolución de sus pacientes. Adicionalmente se describe detalladamente cuál es el problema y cuál es la solución propuesta que cubre las necesidades de los involucrados. La segunda parte trata de contextualizar cómo se da solución al problema detectado y cuáles han sido las diferentes soluciones que han propuesto distintos proyectos basados en aplicaciones móviles y consolas de video juegos que ayudan en la detección del movimiento humano y con ello el monitoreo y seguimiento de la enfermedad de Parkinson. La tercera parte trata del análisis y diseño de software que se realizó para la confección de este proyecto, colocando a disposición los distintos diagramas y arquitecturas que posee la aplicación móvil que se desarrolló. Finalmente se encuentra la implementación del análisis y diseño de software materializado en un sistema llamado Mot-DP, el cual se puso a prueba en diferentes ocasiones en las instalaciones del Centro de Trastornos del Movimiento (CETRAM) de la Universidad de Santiago, con el fin de obtener retroalimentaciones de especialistas y de pacientes que utilizaron este sistema. | N35: https://usach.primo.exlibrisgroup.com/discovery/delivery/56USACH_INST:REPOSITORIO/1226459630006116 | O35: UNIVERSIDAD DE SANTIAGO DE CHILE | P35: DEPARTAMENTO DE INGENIERÍA INFORMÁTICA | Q35: (7) Computer Science | R35: (14) Software Development Fundamentals | S35: enfermedad, solución, pacientes, padecen, parkinson, especialistas, móvil, móviles, parte, seguimiento | T35: (3) Software Design
A36: EDUARDO ALFREDO LAGOS ROSALES | B36: INGENIERÍA CIVIL EN INFORMÁTICA | C36: DIURNA | E36: EDMUNDO LEIVA LOBOS | G36: El enfoque diálogo-acción : caso de las actas dialógicas en reuniones usando tableros Kanban | H36: 2015 | I36: Creative Commons AtribuciónNoComercialCompartirIgual | J36: AUTORIZADO | K36: SI | L36: =IF(K36 = "SI", EXTRA!$C$3, EXTRA!$C$4) | M36: El presente trabajo de titulación presenta el desarrollo de un software de apoyo a reuniones, denominado MeetingViewer. El propósito de esta solución es apoyar la gestión de la memoria del grupo entre reuniones y facilitar la acción eficaz dentro de cualquier tipo de proyecto por medio de un acta electrónica. Esta acta, llamada dialógica, sintetiza fuera de los compromisos y acuerdos - que son típicos ítemes de cualquier reunión - las dudas y desacuerdos junto a las tareas - la acción. El proyecto adopta un marco teórico llamado “artefactos del diálogo” para interpretar las comunicaciones dentro de las reuniones. La pregunta clave que guía el trabajo es: ¿Cómo establecer un seguimiento electrónico reunión a reunión de un proyecto colectivo a partir de aquello que se conversa en equipo (representado por la síntesis dialógica) y las acciones derivadas de esas conversaciones? Para ello, es preciso considerar la experiencia del usuario en términos de trazabilidad, usabilidad y buscabilidad. En esto fue clave la adopción de tres metodologías: Scrumdoro, Desarrollo orientado a pruebas (TDD) y evaluación heurística de Nielsen. Además, se optó por el framework Django con Python. Las principales características de la aplicación Web son: que permite agregar usuarios, proyectos, reuniones, elementos dialógicos, entre otros, además de generar un tablero Kanban completamente funcional, el cual está vinculado al registro de los compromisos asumidos en las reuniones del equipo. El resultado final de este trabajo ha sido validado por el Product Owner resguardo el cumplimiento de los requisitos funcionales como historias de usuario y revisados bajo pruebas de aceptación. A nivel de uso, las últimas reuniones entre el memorista y su profesor guía fueron guiadas por la misma aplicación reportada en este trabajo. | N36: https://usach.primo.exlibrisgroup.com/discovery/delivery/56USACH_INST:REPOSITORIO/1226477860006116 | O36: UNIVERSIDAD DE SANTIAGO DE CHILE | P36: DEPARTAMENTO DE INGENIERÍA INFORMÁTICA | Q36: (7) Computer Science | R36: (15) Software Engineering | S36: reuniones, trabajo, proyecto, reunión, acción, acta, además, aplicación, clave, compromisos | T36: (3) Software Design
A37: ARMANDO ESTEBAN ROJAS MUÑOZ | B37: INGENIERÍA CIVIL EN INFORMÁTICA | C37: DIURNA | E37: ARTURO ÁLVAREZ CEA | G37: Piloto automático integrado en Smartphone para vehículo aéreo no tripulado (UAV) | H37: 2015 | I37: Creative Commons AtribuciónNoComercialCompartirIgual | J37: AUTORIZADO | K37: SI | L37: =IF(K37 = "SI", EXTRA!$C$3, EXTRA!$C$4) | M37: El presente trabajo describe el diseño, implementación y prueba de un sistema de control de vuelo y pilotaje automático para un Vehículo Aéreo No Tripulado (UAV) de ala fija tipo ala volante o ala Zagi, utilizando para ello las capacidades de hardware, tales como memoria, procesador, cámara y sensores, de un teléfono inteligente con sistema operativo Android, con el fin de determinar si los smartphones son una alternativa conveniente para el control de vuelo, tanto técnica como económicamente frente a las opciones ya existentes en el mercado, que permita reducir costos en el desarrollo de Vehículos Aéreos No Tripulados (UAV) y en la complejidad de su operación. Para esto se utiliza una metodología diseñada específicamente para el trabajo de acuerdo al contexto en el que se lleva a cabo y las características propias del problema, derivada de las metodologías de desarrollo en cascada con retroalimentación y de prototipo, con etapas de concepción, estudio, codificación, implementación, pruebas, evaluación y revisión, y entrega, que combinan la investigación, programación y pruebas de laboratorio junto con la asesoría de especialistas. Las pruebas realizadas indican que el teléfono utilizado, un Samsung Galaxy S3 Mini, es capaz de interactuar con el conjunto de sensores y actuadores del UAV a través de una placa integradora IOIO-OTG con baja latencia y aplicando las acciones correctivas adecuadas de manera comparable a los pilotos automáticos comerciales. Se determina, producto del trabajo realizado, la factibilidad de utilizar el teléfono como controlador de vuelo y piloto automático, abriendo la puerta para mejoras y desarrollos derivados en este tema. | N37: https://usach.primo.exlibrisgroup.com/discovery/delivery/56USACH_INST:REPOSITORIO/1226555790006116 | O37: UNIVERSIDAD DE SANTIAGO DE CHILE | P37: DEPARTAMENTO DE INGENIERÍA INFORMÁTICA | Q37: (7) Computer Science | R37: (16) Specialized Platform Development | S37: ala, pruebas, teléfono, trabajo, uav, vuelo, automático, control, desarrollo, implementación | T37: (3) Software Design
A38: JAVIER ALFONSO CÁCERES MIÑO | B38: INGENIERÍA CIVIL EN INFORMÁTICA | C38: DIURNA | E38: EDMUNDO LEIVA LOBOS | G38: Recurso de aprendizaje de usabilidad web : Una aproximación desde la cuarta heurística de Nielsen | H38: 2015 | I38: Creative Commons AtribuciónNoComercialCompartirIgual | J38: AUTORIZADO | K38: SI | L38: =IF(K38 = "SI", EXTRA!$C$3, EXTRA!$C$4) | M38: Este trabajo tiene por objetivo desarrollar un recurso de aprendizaje para apoyar la formación en materia de usabilidad a través de principios heurísticos. Las heurísticas de Nielsen son principios generales para el diseño y reparación de interfaces. Si bien existen algunas fuentes que buscan acercar el concepto de usabilidad a su público, la mayoría se centra en el impacto que tiene la usabilidad en el aprendizaje en lugar de transmitir los principios que favorezcan su práctica. El problema radica en que la usabilidad es una característica descuidada ignorando su impacto sobre la calidad de un producto de software, este concepto demanda mayor atención durante la formación de los profesionales de la informática por lo que se patenta la necesidad de apoyar su aprendizaje. En el desarrollo del proyecto se emplearon tres metodologías: Scrumdoro, variante de Scrum para proyectos desarrollados por una persona que se apoya en la técnica de gestión de tiempo Pomodoro; Desarrollo orientado a pruebas (TDD) y una evaluación heurística aplicada sobre el recurso para medir su usabilidad. La solución propuesta en este trabajo es un recurso de aprendizaje que a través de la cuarta heurística de Nielsen orienta el aprendizaje de principios de usabilidad. La aplicación puede describirse mediante cuatro componentes: Contenido educativo local, repositorio de referencias externas, sistema de evaluación, y módulo de práctica donde los estudiantes aplican la teoría sobre un ejemplo construido con tecnologías de front-end. El trabajo ha sido validado por el Dr. Edmundo Leiva, quien como docente y conocedor de las heurísticas supervisó la selección de contenidos y estrategia de evaluación; como Product Owner resguardó el cumplimiento de las historias de usuario y su revisión bajo pruebas de aceptación. El software desarrollado siguió una serie de pruebas como dicta TDD otorgando un nivel apropiado de calidad del código del recurso. | N38: https://usach.primo.exlibrisgroup.com/discovery/delivery/56USACH_INST:REPOSITORIO/1226618470006116 | O38: UNIVERSIDAD DE SANTIAGO DE CHILE | P38: DEPARTAMENTO DE INGENIERÍA INFORMÁTICA | Q38: (7) Computer Science | R38: (7) Human-Computer Interaction | S38: usabilidad, aprendizaje, principios, recurso, evaluación, pruebas, trabajo, apoyar, calidad, concepto | T38: (3) Software Design
A39: RAFAEL ALEJANDRO SOTO GALLARDO | B39: INGENIERÍA CIVIL EN INFORMÁTICA | C39: DIURNA | D39: MAGÍSTER EN INGENIERÍA INFORMÁTICA | E39: CAROLINA BONACIC CASTRO | G39: Simulador de aplicaciones S4 para pruebas de rendimiento y un estudio sobre la utilización de dispositivos móviles como unidades de procesamiento | H39: 2015 | I39: Atribución Creative Commons | J39: AUTORIZADO | K39: SI | L39: =IF(K39 = "SI", EXTRA!$C$3, EXTRA!$C$4) | M39: El presente trabajo trata del diseño y desarrollo de un simulador para la evaluación del rendimiento de aplicaciones Apache S4 (Plataforma de Procesamiento Stream Distribuido) para multiples escenarios de hardware y software. Además se plantea un estudio respecto de la utilización de teléfonos celulares como recursos adicionales de procesamiento, a los cuales las aplicaciones pueden recurrir en algún momento. Los resultados obtenidos muestran que el simulador propuesto sin celulares logra buenos resultados de predicción de rendimiento considerando los tiempos de procesamiento y comunicación entre los elementos de las aplicaciones S4. El error de la raíz cuadrada de la media (RMSE) muestra valores inferiores a los 2 segundos (5 % de error porcentual absoluto respecto del valor real) en el 76.7 % de las simulaciones, mientras que en el resto con errores mayores pero cercanos a los 5 segundos (15 % de error porcentual absoluto respecto de los valores reales). La version con celulares muestra una disminución en el rendimiento de la aplicación en diferentes configuraciones de simulación. Sin embargo, el adicionar replicación en los elementos que se comunican con los celulares a demostrado notorias mejoras en el rendimiento de la aplicación, acercando los resultados a las curvas de procesamiento sin celulares. | N39: https://usach.primo.exlibrisgroup.com/discovery/delivery/56USACH_INST:REPOSITORIO/1226509760006116 | O39: UNIVERSIDAD DE SANTIAGO DE CHILE | P39: DEPARTAMENTO DE INGENIERÍA INFORMÁTICA | Q39: (7) Computer Science | R39: (16) Specialized Platform Development | S39: celulares, procesamiento, rendimiento, aplicaciones, error, respecto, resultados, absoluto, aplicación, elementos | T39: (19) Research/Investigation
A40: MARCO ANTONIO ACEVEDO BAEZA | B40: INGENIERÍA CIVIL EN INFORMÁTICA | C40: DIURNA | E40: CAROLINA BONACIC CASTRO | G40: Sistema de soporte a educadores en entornos de evaluación y aprendizaje de alumnos con necesidades educativas especiales en áreas cognitivas | H40: 2015 | I40: Atribución Creative Commons | J40: AUTORIZADO | K40: SI | L40: =IF(K40 = "SI", EXTRA!$C$3, EXTRA!$C$4) | M40: Dentro de la Educación Diferencial, los alumnos requieren la adaptación de los materiales que tienen a su alcance dentro de su ambiente educativo. Esta adaptación la define el educador basándose en la observación del trabajo del alumno con determinado material. Este proceso requiere que el educador se encuentre presente al momento de la interacción, situación que a veces no se da, ya sea por la cantidad de alumnos a atender o por la interacción cuando el profesor no se encuentra presente al momento de ésta. A través de entrevistas con educadores, se diseña una herramienta que apoye a los educadores a evaluar el uso del material por parte de los alumnos. Con esto se usa una metodología de trabajo incremental y evolutivo para ir construyendo versiones que se vayan mejorando de acuerdo a los comentarios que tengan los mismos educadores, utilizando un desarrollo exploratorio. Como resultado se tiene una aplicación móvil vista como una herramienta con actividades de apoyo a la enseñanza y, como fuente de datos para determinar el avance de un alumno, que de acuerdo a criterios definidos por los mismos educadores, determinan el grado de avance en cierta actividad. También se tiene un sistema de servicios Web encargado de recoger la información de las actividades realizadas a través de la aplicación, con el fin de construir un conjunto de datos de consulta disponible para los educadores. Finalmente se obtiene una plataforma Web, la cual recoge la información para presentarla al educador de acuerdo a criterios que él mismo ha definido dentro del desarrollo de una actividad. También esta plataforma pretende ser una herramienta de administración donde se gestionan los recursos docentes de ciertos establecimientos y las actividades disponibles que un alumno puede desarrollar, seleccionando actividad y nivel. | N40: https://usach.primo.exlibrisgroup.com/discovery/delivery/56USACH_INST:REPOSITORIO/1226605430006116 | O40: UNIVERSIDAD DE SANTIAGO DE CHILE | P40: DEPARTAMENTO DE INGENIERÍA INFORMÁTICA | Q40: (7) Computer Science | R40: (15) Software Engineering | S40: educadores, actividad, actividades, acuerdo, alumno, alumnos, dentro, educador, herramienta, adaptación | T40: (3) Software Design
A41: NICOLÁS ALFREDO ACEVEDO URZÚA | B41: INGENIERÍA CIVIL EN INFORMÁTICA | C41: DIURNA | D41: MAGÍSTER EN INGENIERÍA INFORMÁTICA | E41: VÍCTOR PARADA DAZA | G41: Coevolución computacional en problemas de optimización combinatoria | H41: 2015 | I41: Atribución Creative Commons | J41: AUTORIZADO | K41: SI | L41: =IF(K41 = "SI", EXTRA!$C$3, EXTRA!$C$4) | M41: En la actualidad a pesar de los multiples estudios encontrados en la literatura, siguen existiendo problemas que no han podido ser resueltos de forma optima en un tiempo polinomial. Entre los ma ́s conocidos y estudiados, se encuentran el problema del vendedor viajero y el problema de la mochila binaria. Estos problemas pertenecen al conjunto de problemas NP-Completo, lo que significa que no se ha determinado un algoritmo capaz de encontrar la solución optima para cualquier instancia del problema con bajo tiempo computacional. Entre los me ́todos utilizados se encuentran los relacionados al proceso evolutivo, entre ellos la Programación Genética, la cual es utilizada para la generación automática de algoritmos mediante la combinación de distintos componentes elementales de heurísticas presentes en la literatura, utilizando conceptos básicos de la evolución como cruzamiento, mutación, reproducción, entre otros. Un concepto también proveniente de la evolución es la co-evolución, la cual ha comenzado a aparecer como complemento a los métodos que utilizan evolución en los últimos años. En este trabajo se evalúa el rendimiento computacional que poseen los algoritmos obtenidos mediante la Programación Genética tradicional en comparación a los algoritmos que se obtienen con la Programación Genética utilizando co-evolución. Para realizar la evaluación computacional se ha seleccionado un conjunto de instancias provenientes de la literatura. Luego de ejecutar los experimentos, se obtienen nuevas híper-heurísticas para cada uno de los problemas mencionados que son evaluadas en un conjunto de instancias de evaluación y analizadas para comparar el rendimiento de estas. Los mejores algoritmos para el problema de la mochila obtienen errores menores al 1%, mientras que los algoritmos para el problema del vendedor viajero tienen un error aproximado de 7%. Los resultados son similares en ambos métodos utilizados para cada uno de los problemas. | N41: https://usach.primo.exlibrisgroup.com/discovery/delivery/56USACH_INST:REPOSITORIO/1226607820006116 | O41: UNIVERSIDAD DE SANTIAGO DE CHILE | P41: DEPARTAMENTO DE INGENIERÍA INFORMÁTICA | Q41: (7) Computer Science | R41: (1) Algorithms and Complexity | S41: algoritmos, evolución, problema, problemas, computacional, conjunto, genética, literatura, obtienen, programación | T41: (19) Research/Investigation
A42: JOEL ALAIN ÁVALOS PINCHEIRA | B42: INGENIERÍA CIVIL EN INFORMÁTICA | C42: DIURNA | E42: CAROLINA BONACIC CASTRO | G42: Software de recomendación de rutinas de entrenamiento evolutivas para ciclistas | H42: 2015 | I42: Creative Commons AtribuciónNoComercialCompartirIgual | J42: AUTORIZADO | K42: SI | L42: =IF(K42 = "SI", EXTRA!$C$3, EXTRA!$C$4) | M42: Este trabajo consiste en la construcción de un Software de recomendación de rutinas de entrenamiento evolutivas para ciclistas, a través de una aplicación móvil para Smartphone, cuyo objetivo es proporcionar una herramienta que permita al ciclista desarrollar rutinas de ejercicios personalizadas. El foco del problema consiste en la poca o nula adaptabilidad de los servicios ofrecidos por aplicaciones móviles para ciclistas, lo que lleva a pautas de entrenamiento mal definidas, poco personalizables y con poco grado de evolución. Además se suma la desmotivación y problemas de salud que aparecen al no realizar un entrenamiento adecuado para cada ciclista. Los enfoques actuales ofrecen diversos grados de personalización y evolución en las rutinas de entrenamiento planteadas, sin embargo el costo de adquisición puede llegar a ser bastante elevado, por lo que la aplicación a desarrollar será completamente gratuita y accesible por cualquier ciclista ya sea amateur o profesional. Para reducir riesgos durante la etapa de desarrollo de la aplicación, se optó por utilizar un modelo de desarrollo evolutivo basado en prototipado, lo que permitió adaptarse frente a los cambios de requisitos surgidos durante las iteraciones de desarrollo del prototipo, además de permitir validar las funcionalidades desarrolladas y obtener un feedback temprano por parte de un experto en ciclismo. Finalmente se aseguró la calidad del Software realizado a través de la elaboración y aplicación de un plan de QA (Quality Assurance) compuesto por pruebas unitarias, pruebas de integración, pruebas de validación, pruebas de sistema y pruebas de aceptación. | N42: https://usach.primo.exlibrisgroup.com/discovery/delivery/56USACH_INST:REPOSITORIO/1226583060006116 | O42: UNIVERSIDAD DE SANTIAGO DE CHILE | P42: DEPARTAMENTO DE INGENIERÍA INFORMÁTICA | Q42: (7) Computer Science | R42: (14) Software Development Fundamentals | S42: pruebas, aplicación, entrenamiento, ciclista, desarrollo, rutinas, además, ciclistas, consiste, desarrollar | T42: (3) Software Design
A43: JORGE ANDRÉS ALBERTO MANUEL FIGUEROA GONZÁLEZ | B43: INGENIERÍA CIVIL EN INFORMÁTICA | C43: DIURNA | E43: MÓNICA VILLANUEVA ILUFI | G43: Sistema de información docente para apoyo a la acreditación de los programas de pregrado del Departamento de Ingeniería Informática de la Universidad de Santiago de Chile | H43: 2015 | I43: Creative Commons AtribuciónNoComercial | J43: AUTORIZADO | K43: SI | L43: =IF(K43 = "SI", EXTRA!$C$3, EXTRA!$C$4) | M43: En el presente trabajo de titulación se desarrolla un sistema Web, cuya finalidad es ser una herramienta de apoyo al proceso de autoevaluación para la acreditación de las carreras de pregrado impartidas en el Departamento de Ingeniería Informática de la Universidad de Santiago de Chile. El sistema automatiza ciertas tareas que se realizan hoy en día manualmente, lo que deriva en muchas horas invertidas en este fin por parte de los integrantes del comité de acreditación del DIINF, coordinado por la Doctora Mónica Villanueva Ilufi. El sistema se construye bajo la metodología ágil para desarrollo de software AUP (Proceso Unificado Ágil), la cual permite evitar la generación excesiva de documentación, para dar paso a entregas periódicas que crean valor para los usuarios finales, además de permitir reaccionar rápidamente frente a cambios en los requerimientos establecidos. Durante el transcurso del proyecto, se sostuvo reuniones con el área de TI de Registro Curricular de la Facultad de Ingeniería, para solicitar el acceso a datos de los docentes y los planes de las carreras del Departamento de Ingeniería Informática, para intentar conseguir una de las fuentes de información del sistema. También, se sostuvo reuniones con el Comité de Acreditación del Departamento de Ingeniería Informática, particularmente con la coordinadora del mismo, con quien se delimitó el alcance del proyecto y se establecieron y validaron los requisitos del sistema. Además, se estuvo presente en reuniones entre la coordinadora y otros integrantes del comité, donde se pudo verificar la poca eficiencia con que se obtenían los datos que genera este sistema. En el presente trabajo se desarrolla un sistema que, previa autenticación, permite la generación de las estadísticas referentes a la docencia, que se requieren para completar el Formulario de Autoevaluación (AcreditaCI, 2015) dispuesto por la Comisión Nacional de Acreditación. | N43: https://usach.primo.exlibrisgroup.com/discovery/delivery/56USACH_INST:REPOSITORIO/1226527810006116 | O43: UNIVERSIDAD DE SANTIAGO DE CHILE | P43: DEPARTAMENTO DE INGENIERÍA INFORMÁTICA | Q43: (7) Computer Science | R43: (15) Software Engineering | S43: sistema, acreditación, ingeniería, comité, departamento, informática, presente, reuniones, además, autoevaluación | T43: (3) Software Design
A44: VÍCTOR MANUEL FLORES SÁNCHEZ | B44: INGENIERÍA CIVIL EN INFORMÁTICA | C44: DIURNA | D44: MAGÍSTER EN INGENIERÍA INFORMÁTICA | E44: FERNANDO RANNOU FUENTES | G44: MassJs: un framework de computación distribuido multiplataforma sobre JavaScript | H44: 2015 | I44: Atribución Creative Commons | J44: AUTORIZADO | K44: SI | L44: =IF(K44 = "SI", EXTRA!$C$3, EXTRA!$C$4) | M44: Hoy en día existe una gran cantidad de recursos computacionales disponibles e infrautilizados como son los teléfonos inteligentes, tablets, ademas de los clásicos equipos de escritorio y cluster computacionales, generalmente todos con conexión permanente a Internet. Sin embargo, el uso de estos dispositivos como un recurso computacional integrado de alto rendimiento, es altamente complejo, ya sea en términos de implementación, configuración y puesta en marcha. Este trabajo presenta el framework MassJs que permite desplegar aplicaciones distribuidas, del tipo embarazosamente paralelas, en cualquier dispositivo capaz de conectarse a Internet y que disponga de un navegador web que soporte JavaScript. MassJs esta estructurado principalmente en dos niveles de abstracción. El primer nivel consiste de un conjunto de servidores que implementan un modelo de computación/comunicación basada en eventos y del tipo Master-Worker. Este nivel es totalmente independiente de la aplicación que se quiera implementar en MassJs. El segundo nivel consiste de un conjunto de interfaces que deben implementarse según la aplicación concreta a ejecutar. El framework MassJs evita realizar algún tipo de configuración en los dispositivos de computo, bastando solo que estos dispositivos se conecten a un sitio web para comenzar a aportar con capacidad de computo. Se implementaron tres aplicaciones concretas para probar el framework, a saber, la búsqueda de números primos, la decodificación de una llave de encriptación y la simulación Monte Carlo del proceso de bioluminiscencia. Los experimentos muestran que se logran speedups cercanos a la linealidad y eficiencias entre 0,7 a 1,0 para cualquiera de las tres aplicaciones concretas implementadas sobre MassJs. A pesar de estos resultados alentadores, se ha concluido que se requiere una gran enjambre de dispositivos de computo procesando para poder compensar la perdida de rendimiento por utilizar un lenguaje interpretado como JavaScript en contraparte con el uso de lenguajes como C/C++ o Java. | N44: https://usach.primo.exlibrisgroup.com/discovery/delivery/56USACH_INST:REPOSITORIO/1226627540006116 | O44: UNIVERSIDAD DE SANTIAGO DE CHILE | P44: DEPARTAMENTO DE INGENIERÍA INFORMÁTICA | Q44: (7) Computer Science | R44: (11) Parallel and Distributed Computing | S44: massjs, dispositivos, aplicaciones, computo, framework, nivel, tipo, aplicación, c, computacionales | T44: (3) Software Design
A45: MARTÍN SANTIAGO GONZÁLEZ SOTOMAYOR | B45: INGENIERÍA CIVIL EN INFORMÁTICA | C45: DIURNA | E45: BRUNO JERARDINO WIESENBORN | G45: Una aplicación móvil desarrollada con Lean Ux para la evaluación psico y sensomotriz previa al examen de conducción | H45: 2015 | I45: Creative Commons AtribuciónNoComercialSinDerivadas | J45: AUTORIZADO | K45: SI | L45: =IF(K45 = "SI", EXTRA!$C$3, EXTRA!$C$4) | M45: El presente trabajo muestra la memoria del desarrollo de una aplicación móvil para Android que permite la evaluación del examen psicotécnico de conducción previo al examen de conducción para obtener la licencia de conducir en Chile. El objetivo del trabajo es permitir a los postulantes a la obtención de la licencia de conducción conocer el examen psicotécnico y verificar si es necesario que se realicen un examen médico de capacidades invalidantes o que generen observaciones en la licencia de conducir. El trabajo se desarrolla a través de la metodología Lean UX, que permite plantear las características de la solución a través de una serie de iteraciones de diseño y desarrollo, validando constantemente con los usuarios y guiando el desarrollo según lo que realizan y plantean respecto a la aplicación. La memoria muestra que el desarrollo cumple con los objetivos planteados en un comienzo, generando una aplicación que permite evaluar los 5 exámenes planteados como características de la solución, agudeza visual, visión de color, audiometría, tiempo de reacción y coordinación visomotriz, y mostrando que en general los mismos usuarios planteaban la necesidad de estos exámenes. Además, a través del desarrollo de la metodología se denota que una gran parte de los usuarios buscan realizar los exámenes de manera lúdica, buscando jugar más que realizar una evaluación para el examen. Este proyecto de título se realiza con el apoyo de la Ilustre Municipalidad de Cerrillos, la cual proporciona información sobre los exámenes y sirve como conexión a los postulantes que planean obtener su licencia en esta comuna. | N45: https://usach.primo.exlibrisgroup.com/discovery/delivery/56USACH_INST:REPOSITORIO/1226566490006116 | O45: UNIVERSIDAD DE SANTIAGO DE CHILE | P45: DEPARTAMENTO DE INGENIERÍA INFORMÁTICA | Q45: (7) Computer Science | R45: (14) Software Development Fundamentals | S45: desarrollo, examen, exámenes, licencia, aplicación, conducción, permite, trabajo, través, usuarios | T45: (3) Software Design
A46: YANINA ELIZABETH OVANDO GUERRERO | B46: INGENIERÍA CIVIL EN INFORMÁTICA | C46: DIURNA | D46: MAGÍSTER EN INGENIERÍA INFORMÁTICA | E46: GONZALO ACUÑA LEIVA | G46: Sistema prototipo de apoyo a la alerta temprana de tsunamis | H46: 2015 | I46: Creative Commons AtribuciónNoComercialCompartirIgual | J46: AUTORIZADO | K46: SI | L46: =IF(K46 = "SI", EXTRA!$C$3, EXTRA!$C$4) | M46: Chile es uno de los países más sísmicos del mundo y, por lo tanto, existe una gran cantidad de pérdidas tanto materiales como humanas debido a terremotos. Por otro lado, el Servicio Sismológico de Chile se encarga de procesar la información obtenida del movimiento de la tierra y es quien debe notificar a las organizaciones pertinentes del evento sísmico ocurrido, proceso que actualmente pierde tiempo valioso. Con la intención de mejorar la detección de sismos, para así obtener información relacionada al origen del mismo, es que se trabajó un conjunto de datos que se compone por sismos registrados entre el 1 de marzo de 2010 y el 30 de marzo de 2010 a lo largo de Chile, a los cuales se realizó un proceso de filtrado, extracción de características, estandarización y luego reducción, para ser utilizados como conjunto de entrenamiento y prueba en las herramientas de inteligencia computacional generadas dentro de una búsqueda en grilla, evaluadas bajo cuatro medidas de error: exactitud, precisión, recall y f1-score. Así, finalmente con el mejor modelo obtenido, calcular y obtener la polarización de aquellas instancias clasificadas como ondas primarias de un sismo. Los resultados señalaron que la medida de error que entrega mejores modelos en la búsqueda en grilla es el f1-score, siendo el modelo seleccionado el que utiliza una ventana de tiempo de 14 segundos para la extracción de características, el cual presenta un 61% de precisión en la clasificación de ondas primarias y un índice de acuerdo discreto. | N46: https://usach.primo.exlibrisgroup.com/discovery/delivery/56USACH_INST:REPOSITORIO/1226551060006116 | O46: UNIVERSIDAD DE SANTIAGO DE CHILE | P46: DEPARTAMENTO DE INGENIERÍA INFORMÁTICA | Q46: (7) Computer Science | R46: (3) Artificial Intelligence | S46: chile, así, búsqueda, características, conjunto, error, extracción, f, grilla, información | T46: (19) Research/Investigation
A47: RODRIGO ANDRÉS MONSALVE LAGOS | B47: INGENIERÍA CIVIL EN INFORMÁTICA | C47: DIURNA | E47: ROBERTO GONZÁLEZ-IBÁÑEZ | G47: Dispositivo de retroalimentación táctil para interfaces naturales y de realidad virtual | H47: 2015 | I47: Atribución Creative Commons | J47: AUTORIZADO | K47: SI | L47: =IF(K47 = "SI", EXTRA!$C$3, EXTRA!$C$4) | M47: En los últimos años se han desarrollado dispositivos que utilizan mecanismos de interacción naturales como: la voz, los gestos y el movimiento del cuerpo. Sin embargo, estos dispositivos carecen de una componente táctil que permita completar la interacción, en especial, en tareas de manipulación. Los dispositivos que entregan retroalimentación táctil actualmente no son de fácil acceso, se encuentran en desarrollo o no incluyen herramientas que permitan la integración con otros dispositivos de realidad virtual o interfaces naturales. Para solventar este problema, se desarrolla un dispositivo que consta de un componente de hardware y un componente de software. El componente de hardware es un guante que entrega retroalimentación táctil a través de seis motores de vibración reubicables, construido con una placa LilyPad Arduino y utilizando materiales de fácil acceso. El componente de software consta de tres APIs de comunicación en C#, JAVA y JavaScript, en conjunto con un software de control para la inicialización y activación de los diferentes motores de vibración e integración de nuevos actuadores sin modificar el software. El desarrollo de hardware se realiza en base a una modificación de Universal Design Method con elementos de Rapid Aplication Development para la etapa de prototipos. El desarrollo de software se basa en la metodología Rapid Aplication Development, utilizando pautas y buenas prácticas para el desarrollo de APIs de diferentes autores. Se realizan evaluaciones técnicas que demuestran que el dispositivo tiene un comportamiento estable, alcanzando hasta 12 milisegundos de latencia al activar seis motores de vibración, valor por debajo del umbral aceptado en investigaciones relacionadas en la literatura, con una autonomía de 30 minutos aproximadamente con una batería de 110 mAh y 300 minutos aproximadamente con una batería de 1000mAh. El trabajo se realiza en el marco del proyecto DICYT No 061519GI | N47: https://usach.primo.exlibrisgroup.com/discovery/delivery/56USACH_INST:REPOSITORIO/1226581070006116 | O47: UNIVERSIDAD DE SANTIAGO DE CHILE | P47: DEPARTAMENTO DE INGENIERÍA INFORMÁTICA | Q47: (7) Computer Science | R47: (16) Specialized Platform Development | S47: componente, software, desarrollo, dispositivos, hardware, motores, táctil, vibración, acceso, apis | T47: (3) Software Design
A48: DAVID IGNACIO AGUILAR BORNE | B48: INGENIERÍA CIVIL EN INFORMÁTICA | C48: DIURNA | E48: MÓNICA VILLANUEVA ILUFI | G48: Enumeración de conjuntos independientes maximales en gráficos polares | H48: 2015 | I48: Creative Commons AtribuciónNoComercialCompartirIgual | J48: AUTORIZADO | K48: SI | L48: =IF(K48 = "SI", EXTRA!$C$3, EXTRA!$C$4) | M48: El siguiente trabajo presenta una solución al problema de enumeración de conjuntos independientes maximales en un grafo perteneciente a la clase polar. Un conjunto independiente corresponde a un subconjunto de vértices de un grafo G, en el que ningún par de vértices es adyacente entre sí, y es maximal si no existe otro conjunto independiente que lo contenga. Enumerar la familia de conjuntos independientes maximales para un grafo cualquiera, pertenece a la clase #P-Completo; sin embargo, en algunas clases particulares se encuentran soluciones en tiempos polinomiales. Un grafo polar corresponde a un grafo G, cuyo conjunto de vértices puede ser dividido en dos grupos A y B, tal que A induce un subgrafo del complemento de G y B induce un subgrafo de G, en que cada uno de sus componentes conexos es un grafo completo en ambos casos. Los grafos bipartitos, split y bisplit corresponden a subclases de la clase polar. Un grafo polar G es incompleto si, para cada conjunto independiente, cada clique tiene al menos un vértice que no es adyacente a ninguno de los vértices del conjunto independiente. El resultado de esta investigación corresponde a un algoritmo que enumera la familia de conjuntos independientes maximales para un grafo polar incompleto cualquiera, y adicionalmente para grafos polares completos de una clique. Los resultados obtenidos permiten verificar que el algoritmo desarrollado es más eficiente que el algoritmo de Tsukiyama et al., para esta clase de grafos. Por otro lado se desarrolla una fórmula que permite determinar una cota superior para el tamaño de la familia de conjuntos independientes maximales en un grafo polar incompleto. | N48: https://usach.primo.exlibrisgroup.com/discovery/delivery/56USACH_INST:REPOSITORIO/1226568830006116 | O48: UNIVERSIDAD DE SANTIAGO DE CHILE | P48: DEPARTAMENTO DE INGENIERÍA INFORMÁTICA | Q48: (7) Computer Science | R48: (1) Algorithms and Complexity | S48: grafo, polar, conjunto, g, clase, conjuntos, independiente, independientes, maximales, vértices | T48: (19) Research/Investigation
A49: VICENTE JAVIER BRAVO PRIDA | B49: INGENIERÍA CIVIL EN INFORMÁTICA | C49: DIURNA | E49: MÓNICA VILLANUEVA ILUFI | G49: Enumeración de conjuntos independientes maximales en gráficos cuasi-triangulados | H49: 2015 | I49: SIN LICENCIA | J49: SIN AUTORIZACIÓN | K49: SI | L49: =IF(K49 = "SI", EXTRA!$C$3, EXTRA!$C$4) | M49: Para grafos triangulados, aquellos para los que existe un esquema de eliminación perfecta, Leung resuelve el problema de encontrar los conjuntos independientes maximales por medio de un algoritmo de backtracking. Un grafo G es quasi-triangulado si permite un esquema de eliminación como una secuencia de vértices simpliciales (cuyo conjunto de adyacencia conforma una clique) y co-simpliciales (el conjunto de adyacencia en el complemento conforma una clique). Este trabajo expone un algoritmo para la enumeración de los conjuntos independientes maximales (cim) de este tipo de grafos, extendiendo la resolución del algoritmo de Leung, de modo que se resuelve el problema en tiempo polinomial en el número de cim con tiempo O(𝛼(n + m + w log w + 𝛼)). Para un grafo cualquiera este problema es #P-completo. | N49: https://usach.primo.exlibrisgroup.com/discovery/delivery/56USACH_INST:REPOSITORIO/1233007830006116 | O49: UNIVERSIDAD DE SANTIAGO DE CHILE | P49: DEPARTAMENTO DE INGENIERÍA INFORMÁTICA | Q49: (7) Computer Science | R49: (1) Algorithms and Complexity | S49: algoritmo, problema, adyacencia, cim, clique, conforma, conjunto, conjuntos, eliminación, esquema | T49: (11) Software Engineering Models and Methods
A50: JORGE FRANCISCO CABEZAS MORALES | B50: INGENIERÍA DE EJECUCIÓN EN COMPUTACIÓN E INFORMÁTICA | C50: DIURNA | E50: LUIS RÍOS SEPÚLVEDA | G50: Rediseño del proceso de negocio asociado al servicio de arriendo de grúas horquilla para la empresa Grúas M&L Ltda. | H50: 2015 | I50: Creative Commons AtribuciónNoComercialCompartirIgual | J50: AUTORIZADO | K50: SI | L50: =IF(K50 = "SI", EXTRA!$C$3, EXTRA!$C$4) | M50: El objetivo de esta memoria consiste en rediseñar el proceso de negocio existente en la empresa de servicio de arriendo de grúas horquilla Grúas M&L a modo de tener la base para implantar un proceso de mejora continua. En esta memoria se revisan los conceptos asociados a una perspectiva de proceso para las operaciones de la organización, se analiza los procesos existentes en la empresa y se implementa el rediseño optimizado mediante un Sistema Gestor de Procesos de Negocio (BPMS). Al concretar el objetivo se resuelven varios aspectos existentes en la empresa que afectan a la eficiencia de la organización. Uno de ellos es la perspectiva estratégica, en la cual acciones básicas para la toma de decisiones tienen una complejidad excesiva debido al bajo nivel de automatización de los datos, que prácticamente imposibilita la generación de información. Desde el punto de vista de la eficiencia el problema afecta de forma directa a los trabajadores quienes deben realizar labores de forma innecesaria por la baja interconexión de los datos que en caso de no ser controlado en variados puntos del proceso se producen inconsistencias que afectan a las distintas áreas. A pesar de lo reciente de la tecnología utilizada para realizar la implementación de los procesos de negocio, los objetivos de este proyecto se han completado de forma exitosa permitiendo tener una base para futuras etapas de mejora que hagan uso de las capacidades de las tecnologías de la información e inteligencia de negocios. | N50: https://usach.primo.exlibrisgroup.com/discovery/delivery/56USACH_INST:REPOSITORIO/1226468510006116 | O50: UNIVERSIDAD DE SANTIAGO DE CHILE | P50: DEPARTAMENTO DE INGENIERÍA INFORMÁTICA | Q50: (7) Computer Science | R50: (15) Software Engineering | S50: proceso, empresa, forma, negocio, procesos, afectan, base, datos, eficiencia, existentes | T50: (11) Software Engineering Models and Methods
A51: BENJAMÍN SAMUEL ELÍAS QUINTANA OVIEDO | B51: INGENIERÍA DE EJECUCIÓN EN COMPUTACIÓN E INFORMÁTICA | C51: DIURNA | E51: CAROLINA BONACIC CASTRO | F51: FABIÁN RIQUELME CSORI | G51: Twinfluentials : un algoritmo para medir influencia en líderes de opinión | H51: 2015 | I51: Creative Commons AtribuciónNoComercialCompartirIgual | J51: AUTORIZADO | K51: SI | L51: =IF(K51 = "SI", EXTRA!$C$3, EXTRA!$C$4) | M51: El estudio de líderes de opinión de políticos chilenos en redes sociales se ha estudiado con medidas muy simples, como por ejemplo contar cantidad de seguidores que estos tienen. Es por eso que se pretende crear una nueva medida de influencia en la red social Twitter que considere más variables para este tipo de estudios y que pueda ser aplicable al contexto de la política. Para esto se desarrolló la herramienta Twinfluentials, la cual utiliza variables como la cantidad de seguidores, retweets y respuestas hechas sobre el usuario analizado; y además a través de técnicas de análisis de sentimientos analiza cuales de estas respuestas son de carácter positivo o negativo, mediante la implementación de un clasificador bayesiano ingénuo. Los resultados de esta aplicación sobre una muestra de cincuenta cuentas de Twitter asociadas a políticos chilenos fueron comparados con los de otras herramientas de la literatura para comparar si existe alguna relación entre ellas, y a qué pueden deberse las relaciones. Así también fueron comparadas las medidas de influencia de Twitter con las actuales encuestas de aprobación utilizadas en la política chilena para ver si los resultados están relacionados entre ellos, y conocer si las medidas de influencia de Twitter son herramientas válidas como medidas de aprobación a los políticos chilenos. La medida puede ser usada como una nueva fuente de información sobre la aprobación en política, pero sólo restringida al ámbito de la rede social Twitter. | N51: https://usach.primo.exlibrisgroup.com/discovery/delivery/56USACH_INST:REPOSITORIO/1226567100006116 | O51: UNIVERSIDAD DE SANTIAGO DE CHILE | P51: DEPARTAMENTO DE INGENIERÍA INFORMÁTICA | Q51: (7) Computer Science | R51: (3) Artificial Intelligence | S51: twitter, medidas, aprobación, chilenos, influencia, política, políticos, si, cantidad, herramientas | T51: (19) Research/Investigation
A52: ADRIÁN ESTEBAN GARRIDO GOICOVIC | B52: INGENIERÍA DE EJECUCIÓN EN COMPUTACIÓN E INFORMÁTICA | C52: DIURNA | E52: JUAN IGNACIO ITURBE ARAYA | G52: Prototipo de aplicación para el SO Android indicadora del riesgo de confidencialidad e integridad de los datos sensibles del usuario | H52: 2015 | I52: Atribución Creative Commons | J52: AUTORIZADO | K52: SI | L52: =IF(K52 = "SI", EXTRA!$C$3, EXTRA!$C$4) | M52: Los dispositivos móviles ofrecen una cantidad enorme de servicios que permiten realizar muchas funcionalidades de manera muy sencilla y económica para los usuarios, es por esto que su uso se incremento sustancialmente desde el an ̃o 2008, cuando fue lanzado el primer smartphone. Los usuarios cuentan con qué la información que guardan en sus dispositivos esta a buen resguardo, pero eso no necesariamente es ası. Las aplicaciones acceden a recursos del dispositivo y los administran para ofrecer un servicio, pero no se sabe si dicha gestión otorga al usuario confidencialidad. Para solucionar dicha problemática, se crearon sistemas capaces de identificar el uso de los datos por parte de las aplicaciones y realizar seguimiento de los mismos, para que los usuarios tomen medidas de prevención. El problema de ellas es que para que sea posible que entreguen resultados las aplicaciones riesgosas deben estar funcionando, lo que permite que al menos una vez la información del usuario se vea expuesta, y esto pudiera ser muy perjudicial para él mismo. En este trabajo se propone un sistema que revisa el código fuente de las aplicaciones y evalúa el nivel de riesgo asociado a la gestión de la información y a través de una aplicación móvil se informa a los usuarios su nivel de confidencialidad de las aplicaciones que tienen instaladas en el dispositivo. La metodología utilizada para el desarrollo del proyecto fue Mobile-D, ya que es considerada una metodología ágil diseñada para una rápida creación de software para dispositivos móviles en grupos pequeños de trabajo. Este es un proyecto externo a la universidad, ya que fue planteado por un investigador de Malware de McAfee (Fernando Ruiz) con la intención de investigar la gestión que realizan ciertas aplicaciones con la información contenida en el dispositivo. | N52: https://usach.primo.exlibrisgroup.com/discovery/delivery/56USACH_INST:REPOSITORIO/1226475720006116 | O52: UNIVERSIDAD DE SANTIAGO DE CHILE | P52: DEPARTAMENTO DE INGENIERÍA INFORMÁTICA | Q52: (7) Computer Science | R52: (14) Software Development Fundamentals | S52: aplicaciones, información, usuarios, dispositivo, dispositivos, gestión, confidencialidad, dicha, metodología, móviles | T52: (19) Research/Investigation
A53: JORGE EDUARDO REBOLLEDO GONZÁLEZ | B53: INGENIERÍA DE EJECUCIÓN EN COMPUTACIÓN E INFORMÁTICA | C53: DIURNA | E53: LUIS RÍOS SEPÚLVEDA | G53: Desarrollo de un sistema de administración para el Salón de Belleza Ártico | H53: 2015 | I53: Atribución Creative Commons | J53: AUTORIZADO | K53: SI | L53: =IF(K53 = "SI", EXTRA!$C$3, EXTRA!$C$4) | M53: El Salón de Belleza, utiliza procedimientos no formales para llevar a cabo la administración de los trabajos realizados por los empleados, además la gestión de los clientes se ha convertido en un problema al no contar con la información de estos de manera oportuna. Otro de los problemas detectados tiene relación con la agenda de las horas de atención a clientes. Por otro lado se requiere un sistema capaz de calcular las remuneraciones de los empleados de acuerdo a los trabajos realizados. El sistema contempla la administración de clientes, trabajos, empleados, pagos, productos y agenda de citas. A lo largo del capitulo de Desarrollo de la solución se observa las etapas de la metodología Scrum. En una primera parte se hace la toma de requerimientos del sistema para obtener las historias de usuario y así desarrollar un Product Backlog del que se desprenden los elementos a desarrollar en cada Sprint del proyecto, además, se observa el avance del proyecto en forma de entregables. Como resultado del desarrollo del sistema, se obtiene una página WEB residente en Amazon Web Services (en modo de producción, actualmente en la dirección: http://52.89.14.128) en la cual los administradores y trabajadores del Salón pueden ingresar desde cualquier computador con internet, en conjunto con su usuario y contraseña para acceder a las diferentes características del sistema. Como conclusiones del trabajo, se plantea continuar desarrollando módulos para extender el sistema hacia otros salones y así poder comercializarlo. | N53: https://usach.primo.exlibrisgroup.com/discovery/delivery/56USACH_INST:REPOSITORIO/1226608300006116 | O53: UNIVERSIDAD DE SANTIAGO DE CHILE | P53: DEPARTAMENTO DE INGENIERÍA INFORMÁTICA | Q53: (7) Computer Science | R53: (15) Software Engineering | S53: sistema, clientes, empleados, trabajos, además, administración, agenda, así, desarrollar, desarrollo | T53: (1) Software Requirements
A54: PAZ CAROLINA BUSTOS MENA | B54: INGENIERÍA DE EJECUCIÓN EN COMPUTACIÓN E INFORMÁTICA | C54: DIURNA | E54: EDMUNDO LEIVA LOBOS | G54: Portal web corporativo para la organización REASE | H54: 2015 | I54: Creative Commons AtribuciónNoComercialCompartirIgual | J54: AUTORIZADO | K54: SI | L54: =IF(K54 = "SI", EXTRA!$C$3, EXTRA!$C$4) | M54: El presente trabajo de titulación muestra el desarrollo de un sistema web para la Red Nacional de Aprendizaje y Servicio, REASE. Esta institución funciona hace más de tres años, pero ahora está en transición a convertirse en una organización sin fines de lucro. Su fin es la promoción y difusión de la metodología de aprendizaje denominada Aprendizaje Servicio, AS. REASE precisa contar con un sitio web que permita a los visitantes enterarse de su organización y brindarles a sus miembros servicios de información y de interrelación entre sus miembros. El AS posee una doble intencionalidad: formar seres humanos solidarios y desarrollar habilidades propias del currículo. Por ejemplo, una feria libre (socio comunitario) y un curso de contabilidad. Aquí, los feriantes no saben cómo separar sus dineros propios de la venta de sus productos y los estudiantes saben teóricamente “flujos de caja” pero no conocen el mundo. AS parte con un diseño e implementación de un proyecto de intervención social donde todos aprenden y reflexionan. En AS, también aparece, en ciertos casos, un tercer stakeholder llamado “vinculador social” que cuida la relación socio-servicio-profesores en el tiempo. Los requerimientos del sitio se extrajeron del trabajo de Carolina Orrego. Luego, a través de la metodología AUP, el tablero Kanban, Ruby on Rails y MySQL sobre Linux se desarrolló la aplicación. Además, el sitio permite que los stakeholders del AS participen de un marketplace de ofertas y solicitudes de servicios. Por otro lado, permite a los visitantes ocasionales darse una idea clara de REASE y sus eventos. Finalmente, se estableció un rol para administrar el contenido del sitio dinámicamente. Para la etapa de validación, el sitio tuvo la concurrencia de miembros activos que mostraron el cumplimiento de los objetivos funcionales que el sitio había establecido. | N54: https://usach.primo.exlibrisgroup.com/discovery/delivery/56USACH_INST:REPOSITORIO/1226523430006116 | O54: UNIVERSIDAD DE SANTIAGO DE CHILE | P54: DEPARTAMENTO DE INGENIERÍA INFORMÁTICA | Q54: (7) Computer Science | R54: (14) Software Development Fundamentals | S54: sitio, as, aprendizaje, miembros, rease, servicio, metodología, organización, permite, saben | T54: (2) Software Architecture
A55: VÍCTOR ALONSO REYES TAPIA | B55: INGENIERÍA DE EJECUCIÓN EN COMPUTACIÓN E INFORMÁTICA | C55: DIURNA | E55: ROSA MUÑOZ CALANCHIE | G55: Objeto de aprendizaje para Blowfish | H55: 2015 | I55: Creative Commons AtribuciónNoComercial | J55: AUTORIZADO | K55: SI | L55: =IF(K55 = "SI", EXTRA!$C$3, EXTRA!$C$4) | M55: Los modelos educativos actuales distan de lo que eran hace algunos años, la inclusión de la tecnología, y junto con su desarrollo ha provocado cambios profundos sobre el cómo aprende un estudiante, el surgimiento de nuevas herramientas, más flexibles y adaptables a cada estudiante como son los Objetos de Aprendizaje, han resultado ser un gran complemento a las clases tradicionales, motivo por el cual se han podido masificar en este último tiempo. Sin embargo, y a causa de esa masificación, se produjo la necesidad de normalizar y tipificar que son estos objetos, y tan importante como eso, el cómo fabricarlos de manera correcta, y una de las soluciones con las que cuenta el Departamento de Ingeniería Informática de la Universidad de Santiago de Chile, es la metodología CPIS, capaz de guiar al desarrollador facilitando la entrega de bueno productos finales. El principal resultado de este proyecto, es el desarrollo de un objeto de aprendizaje (O.A.) que está enfocado en el algoritmo de Blowfish, junto con su correspondiente documentación que respalde su funcionamiento, pruebas y ventajas de poseerlo. Blowfish es un algoritmo de cifrado simétrico, con clave de tamaño variable entre 32 y 448 bits, de bloque, que utiliza la estructura Feistel, su estudio resulta interesante por dos aspectos principales, por un lado es un complemento a la materia vista en cursos relacionados a la seguridad en redes, como Criptografía y Protocolos de Seguridad, pero además es un algoritmo que no tiene patente, que junto con el hecho de ser considerado un sistema seguro por su capacidad de resistir ataques, lo convierten en una buena opción para futuros proyectos del departamento que requieran la inclusión de un algoritmo de cifrado. El objeto de aprendizaje ha sido validado en si contenido por la profesora del electivo Criptografía y Protocolos de Seguridad, como experta docente, y por estudiantes del Departamento de Ingeniería Informática (DIINF) que cursaron la asignatura de Redes Computacionales y el electivo de Criptografía y Protocolos de Seguridad. | N55: https://usach.primo.exlibrisgroup.com/discovery/delivery/56USACH_INST:REPOSITORIO/1226569470006116 | O55: UNIVERSIDAD DE SANTIAGO DE CHILE | P55: DEPARTAMENTO DE INGENIERÍA INFORMÁTICA | Q55: (7) Computer Science | R55: (15) Software Engineering | S55: algoritmo, seguridad, aprendizaje, criptografía, departamento, junto, protocolos, blowfish, cifrado, complemento | T55: (11) Software Engineering Models and Methods
A56: SEBASTIÁN GABRIEL ESCOBAR TRONCOSO | B56: INGENIERÍA DE EJECUCIÓN EN COMPUTACIÓN E INFORMÁTICA | C56: DIURNA | E56: JUAN IGNACIO ITURBE ARAYA | G56: Prototipo de aplicación móvil para denuncias y eventos geolocalizados con evidencia multimedia | H56: 2015 | I56: SIN LICENCIA | J56: SIN AUTORIZACIÓN | K56: SI | L56: =IF(K56 = "SI", EXTRA!$C$3, EXTRA!$C$4) | M56: El presente proyecto de tesis da a conocer la elaboración de un sistema para registro de eventos y denuncias utilizando geolocalización y evidencia multimedia. (Proyecto Externo) Propuesto como trabajo para la obtención del título de Ingeniero de Ejecución en Computación e Informática. Debido al auge de las tecnologías móviles y a la creciente necesidad de solucionar problemas mediante esta tecnología, es que se hace necesario que la información relacionada a estos problemas esté disponible para los usuarios de manera precisa y oportuna. En este trabajo de titulación, se desarrolla un prototipo funcional de aplicación móvil para el sistema operativo Android, que permite el registro de denuncias y eventos que estén ocurriendo en determinados lugares, utilizando como base principal la geolocalización y evidencia multimedia. La información atribuida a las denuncias y acontecimientos podrá ser visualizada en la aplicación mediante un mapa que indique los lugares donde ocurre un acto ilícito, un hecho irregular o un acontecimiento en particular. Los usuarios podrán adjuntar evidencia multimedia y calificar las denuncias y eventos que sean de su interés. El trabajo es realizado utilizando la metodología de desarrollo Mobile-D, la cual se compone de cinco fases. La primera de ellas es la fase de exploración, la cual establece los requerimientos del proyecto y sus alcances. La segunda etapa es la fase de inicialización que considera la preparación de los recursos físicos, técnicos y humanos que permiten la construcción del sistema. La tercera etapa es la fase de producción, en la cual se implementa la solución utilizando un ciclo de desarrollo iterativo e incremental. Finalmente sigue la fase de estabilización y fase de pruebas, en donde se finaliza la integración del producto y se realizan las pruebas pertinentes para su entrega final. El cierre del proyecto contempla su publicación en la tienda de aplicaciones Google Play. | N56: https://usach.primo.exlibrisgroup.com/discovery/delivery/56USACH_INST:REPOSITORIO/1232493710006116 | O56: UNIVERSIDAD DE SANTIAGO DE CHILE | P56: DEPARTAMENTO DE INGENIERÍA INFORMÁTICA | Q56: (7) Computer Science | R56: (14) Software Development Fundamentals | S56: fase, denuncias, proyecto, utilizando, eventos, evidencia, multimedia, sistema, trabajo, aplicación | T56: (3) Software Design
A57: JORGE BERMECIDES SALAZAR CASTRO | B57: INGENIERÍA DE EJECUCIÓN EN COMPUTACIÓN E INFORMÁTICA | C57: DIURNA | E57: LUIS RÍOS SEPÚLVEDA | G57: Desarrollo de un plan de recuperación ante desastres para procesos críticos de TI | H57: 2015 | I57: Atribución Creative Commons | J57: AUTORIZADO | K57: SI | L57: =IF(K57 = "SI", EXTRA!$C$3, EXTRA!$C$4) | M57: El presente proyecto de titulación ataca una problemática crítica de la empresa, la existencia de falencias graves de seguridad, las que afectan la respuesta efectiva ante desastres naturales o intencionales. No se tiene un plan de acción acorde para enfrentar una emergencia que podría afectar severamente su continuidad de negocio. El área de TI de la empresa tiene varios procesos críticos que soportan otras unidades de negocio, las cuales basan la mayoría de los procesos digitales en el área de la informática. Ante este escenario nace la necesidad de crear un plan de recuperación ante desastres acorde a la empresa. Se utiliza un método usado por las divisiones regionales de la empresa, pero adaptado a la división chilena de la misma. Esta metodología propone un análisis previo de la arquitectura utilizada en la empresa, también definir estrategias de contingencia usadas por la empresa, además de cambios previos antes de implementar el plan, pasos a seguir ante una emergencia y la posterior vuelta a la normalidad. Los beneficios de la solución propuesta son principalmente económicos. Si bien la empresa no pierde directamente ventas por la pérdida o interrupción de los sistemas informáticos, se pueden perder muchos tiempo en recuperar los datos que son importantes para el negocio. La implementación de este plan aliviana las posibles pérdidas de la información crítica para la empresa. Este proyecto forma parte de un proyecto externo a la Universidad, adecuado a la división regional de la empresa. | N57: https://usach.primo.exlibrisgroup.com/discovery/delivery/56USACH_INST:REPOSITORIO/1226441320006116 | O57: UNIVERSIDAD DE SANTIAGO DE CHILE | P57: DEPARTAMENTO DE INGENIERÍA INFORMÁTICA | Q57: (7) Computer Science | R57: (12) Security | S57: empresa, plan, negocio, proyecto, acorde, crítica, desastres, división, emergencia, procesos | T57: (13) Software Security
A58: CARLOS ALFREDO BARRERA PULGAR | B58: INGENIERÍA CIVIL EN INFORMÁTICA | C58: DIURNA | D58: MAGÍSTER EN INGENIERÍA INFORMÁTICA | E58: ROBERTO GONZÁLEZ-IBÁÑEZ | G58: Evaluación de gestos táctiles en la interacción con objetos de información digital | H58: 2015 | I58: TODOS LOS DERECHOS RESERVADOS | J58: AUTORIZADO | K58: NO | L58: =IF(K58 = "SI", EXTRA!$C$3, EXTRA!$C$4) | N58: https://usach.primo.exlibrisgroup.com/discovery/delivery/56USACH_INST:REPOSITORIO/1226560520006116 | O58: UNIVERSIDAD DE SANTIAGO DE CHILE | P58: DEPARTAMENTO DE INGENIERÍA INFORMÁTICA | Q58: (28) It does not belong to the computer science field. | R58: (18) It does not belong to the computer science field. | S58: NA | T58: (20) It does not belong to the computer science field.
A59: MARCIAL NATALIO HERNÁNDEZ SÁNCHEZ | B59: INGENIERÍA DE EJECUCIÓN EN COMPUTACIÓN E INFORMÁTICA | C59: DIURNA | E59: JOSÉ LUIS JARA VALENCIA | G59: PYTAXO: Generador de preguntas de opción múltiple para el curso de fundamentos de programación | H59: 2015 | I59: Creative Commons AtribuciónNoComercialCompartirIgual | J59: AUTORIZADO | K59: SI | L59: =IF(K59 = "SI", EXTRA!$C$3, EXTRA!$C$4) | M59: La construcción de preguntas de opción múltiple (MCQ) siempre se ha realizado de forma lineal, asumiendo que su utilización se realiza al mismo tiempo y lugar, en determinados instrumentos de evaluación. Premisas que la coordinación de Fundamentos de Computación y Programación (FCyP) dejó de cumplir, al integrarse al módulo básico de ingeniería, aumentando su cantidad de alumnos examinados de 60~90 a 1.300 aproximadamente. Ante esta problemática se ha creado el generador de ítemes Pytaxo utilizando la metodología Feature Driven Development, modelando el sistema usando casos de uso ETVX (Entry-Task- Verification-Exit), donde cada caso representa la confección de un módulo de software, que genera mediante algoritmos combinatoriales y exhaustivos, variantes de un tipo de pregunta MCQ, ligado a un determinado objetivo de evaluación perteneciente a la Taxonomía de Bloom. Generando desde una entrada XML, un Moodle XML que contiene todas las preguntas generadas. Para la validación, se han realizado tres etapas. La primera somete a Pytaxo a pruebas de caja negra con inyección de errores, en las entradas de los siete módulos creados, obteniendo una tolerancia media de 86.61%. La segunda etapa verifica la diferenciación de los ítemes provenientes de diferentes módulos, analizando la información obtenida de una encuesta realizada por 9 examinadores, mediante un dendograma utilizando el algoritmo UPGMA usando una matriz de similaridad con los coeficientes de correlación de Pearson, mostrando que los ítemes basados en un script Python abarcan objetivos evaluativos más específicos de aquellos que no lo usan. Finalmente se analiza el desempeño de cuatro tipos de ítemes, tras su uso en los controles de laboratorio de FCyP usando la plataforma Moodle, donde tres tuvieron un buen desempeño en función de las métricas de Facilidad y Discriminación, y respecto al tiempo, no se llega a una conclusión clara debido a la alta dispersión en los tiempos de resolución. | N59: https://usach.primo.exlibrisgroup.com/discovery/delivery/56USACH_INST:REPOSITORIO/1226477940006116 | O59: UNIVERSIDAD DE SANTIAGO DE CHILE | P59: DEPARTAMENTO DE INGENIERÍA INFORMÁTICA | Q59: (7) Computer Science | R59: (15) Software Engineering | S59: ítemes, usando, desempeño, evaluación, fcyp, mcq, mediante, moodle, módulo, módulos | T59: (11) Software Engineering Models and Methods
A60: FABIÁN IGNACIO ACUÑA FLORES | B60: INGENIERÍA DE EJECUCIÓN EN COMPUTACIÓN E INFORMÁTICA | C60: DIURNA | E60: ROSA MUÑOZ CALANCHIE | G60: Desarrollo de objetos de aprendizaje para apoyar el estudio de las redes IP | H60: 2015 | I60: Creative Commons AtribuciónNoComercialCompartirIgual | J60: AUTORIZADO | K60: SI | L60: =IF(K60 = "SI", EXTRA!$C$3, EXTRA!$C$4) | M60: En la actualidad la inclusión de tecnologías de la información (TIC) al área de la educación ha permitido generar nuevas herramientas que apoyen el proceso enseñanza- aprendizaje, esto genera un beneficio tanto a los estudiantes como educadores. Es en este contexto surgen los sistemas de gestión de aprendizaje alojados en la Web, los que permiten la reutilización de los recursos y con acceso en cualquier momento que se cuente con una conexión a Internet. Con esta herramienta se pueden generar aplicaciones con material didáctico que apoye el estudio de temas complejos como son las Redes IP. Es por lo anteriormente mencionado que se elaboran y validan Objetos de Aprendizaje como herramientas que permiten tener interactividad entre los estudiantes y la aplicación, esta interactividad se logra incluyendo imágenes, texto, videos, actividades y evaluaciones referentes al Protocolo IP. Para lograr esto, lo primero es detectar el estilo de aprendizaje predominante que tienen los usuarios finales. Luego se desarrollan herramientas educativas con la metodología CPIS, una vez desarrolladas se somete a evaluaciones realizadas por los alumnos y validaciones de tipo pedagógica, respecto del diseño y de contenido, para obtener una aproximación del aporte que proporciona el objeto de aprendizaje. Como producto final de este trabajo se obtienen tres objetos de aprendizaje que apoyan el estudio de las Redes IP. | N60: https://usach.primo.exlibrisgroup.com/discovery/delivery/56USACH_INST:REPOSITORIO/1226508730006116 | O60: UNIVERSIDAD DE SANTIAGO DE CHILE | P60: DEPARTAMENTO DE INGENIERÍA INFORMÁTICA | Q60: (7) Computer Science | R60: (15) Software Engineering | S60: aprendizaje, herramientas, ip, estudiantes, estudio, evaluaciones, generar, interactividad, objetos, permiten | T60: (1) Software Requirements
A61: JOSÉ MIGUEL CABRERA BRAVO | B61: INGENIERÍA DE EJECUCIÓN EN COMPUTACIÓN E INFORMÁTICA | C61: DIURNA | E61: HECTOR ANTILLANCA ESPINA | G61: Sistema colaborativo para el desarrollo de interfaces gráficas | H61: 2015 | I61: Atribución Creative Commons | J61: AUTORIZADO | K61: SI | L61: =IF(K61 = "SI", EXTRA!$C$3, EXTRA!$C$4) | M61: Internet nació como un medio de comunicación, para mitigar las distancias y hacer más fácil la vida de quienes la utilizan, pero a pesar de todas las herramientas existentes hoy en día no se ha podido igualar la comunicación presencial, aún es necesario encontrarse para desarrollar reuniones, trabajos, etc. Cuando el encuentro se hace imposible, ¿Estos grupos, pierden la posibilidad de desarrollar lo que debían hacer? Este proyecto aborda una aspecto de esta problemática apoyando el trabajo que realizan los desarrolladores de software, y hace hincapié en un tema que a veces pasa desapercibido a la hora de construir un software, pero su importancia no deja de ser ya que es la parte en donde los usuarios del software se acercan más, se refiere al trabajo de diseño de las interfaces de usuarios. En el presente trabajo se adquieren requerimientos, se diseñan y codifica una aplicación Web para la construcción de interfaces de forma colaborativa realizando actividades de una metodología ágil de modo que permite la flexibilidad necesaria para los cambios de requerimiento, la incorporación de diagramas para facilitar el diseño y la división en iteraciones que facilitan la implementación. Por último se sometió a pruebas con el usuario para recibir retroalimentación y así implementar mejoras. El resultado de esto fue una aplicación que se encuentra actualmente disponible en un sitio Web de desarrollo, permite desarrollar interfaces en forma de bosquejo de manera colaborativa de manera que ayuda en una parte importante del desarrollo de software. | N61: https://usach.primo.exlibrisgroup.com/discovery/delivery/56USACH_INST:REPOSITORIO/1226618300006116 | O61: UNIVERSIDAD DE SANTIAGO DE CHILE | P61: DEPARTAMENTO DE INGENIERÍA INFORMÁTICA | Q61: (7) Computer Science | R61: (15) Software Engineering | S61: software, desarrollar, interfaces, trabajo, aplicación, colaborativa, comunicación, desarrollo, diseño, forma | T61: (3) Software Design
A62: RODRIGO WERNER MARTÍN QUIJADA | B62: - | D62: MAGÍSTER EN INGENIERÍA INFORMÁTICA | E62: VÍCTOR PARADA DAZA | G62: Optimización dinámica del confort térmico de un espacio habitable, mediante algoritmo genético dinámico | H62: 2015 | I62: Creative Commons AtribuciónNoComercialSinDerivadas | J62: AUTORIZADO | K62: SI | L62: =IF(K62 = "SI", EXTRA!$C$3, EXTRA!$C$4) | M62: El problema a enfrentar en la tesis corresponde a la optimización del confort térmico en un espacio habitable, mediante la configuración de una membrana adaptable de fachada. Ésta, permite controlar de forma dinámica la ganancia térmica por ingreso de la luz solar y la ventilación del espacio en estudio. Se compone de 3 elementos independientes (celosías), cada uno compuesto por dos hojas articuladas y que pueden desplazarse verticalmente para abatirse una sobre otra formando un alero o cerrarse verticalmente clausurando el ventanal. Estos 3 elementos independientes permiten una reacción asimétrica según el ángulo solar incidente (mañana o tarde). Para resolver el problema se propone el uso de un algoritmo evolutivo que optimice en forma dinámica, evaluando las condiciones de configuración de la membrana en función de la temperatura y ventilación interior producida, considerando los datos climáticos estadísticos para la ciudad de Santiago. La función de evaluación de la optimización corresponde a la condición de confort térmico calculada mediante el método Fanger. Como hipótesis de trabajo se propone, que el problema dinámico de control de fachada puede ser enfrentado mediante el uso de un algoritmo genético (AG) como mecanismo de control. Las características de adaptabilidad de un AG lo hacen adecuado para el tipo de problema de optimización dinámico (POD) que se produce al optimizar sobre un ambiente definido por los cambios dinámicos en los datos climáticos. Para comparar la efectividad de los resultados del experimento, se contrasto con tres escenarios alternativos de control. Como principales conclusiones, se obtiene que el AG propuesto es robusto para cualquier día del año, obteniendo resultados eficientes para los días de muestra seleccionados, presentando una buena velocidad de recuperación de valores óptimos luego de los diferentes tipos de cambios producidos en los datos climáticos, en las diferentes horas estudiadas. Esto se logra, producto de la calibración de los parámetros de elitismo y mutación. El AG es capaz de seguir la oscilación térmica anual produciendo eficiencias comparativas en relación a los otros métodos analizados, durante 9 de los 12 meses del año. Desde Enero a Mayo, y luego desde Septiembre a Diciembre, siendo especialmente positivo en los meses de verano. El mejor desempeño se produce en estos días de verano, en donde las características de configuración de la membrana propuesta, logran un resultado óptimo en el confort térmico interior durante un periodo diario mayor. | N62: https://usach.primo.exlibrisgroup.com/discovery/delivery/56USACH_INST:REPOSITORIO/1226549660006116 | O62: UNIVERSIDAD DE SANTIAGO DE CHILE | P62: DEPARTAMENTO DE INGENIERÍA INFORMÁTICA | Q62: (13) Engineering | R62: (1) Algorithms and Complexity | S62: ag, problema, climáticos, configuración, confort, control, datos, mediante, membrana, optimización | T62: (19) Research/Investigation
A63: FELIPE ALFREDO NAVARRO VARGAS | B63: - | D63: MAGÍSTER EN INGENIERÍA INFORMÁTICA | E63: VÍCTOR PARADA DAZA | F63: NELSON MORALES | G63: Un algoritmo genético paralelo y distribuido para el agendamiento de bloques en minas a cielo abierto | H63: 2015 | I63: Atribución Creative Commons | J63: AUTORIZADO | K63: SI | L63: =IF(K63 = "SI", EXTRA!$C$3, EXTRA!$C$4) | M63: El objetivo de este estudio es diseñar un Algoritmo Genético Paralelo (AGP) para el problema de agendamiento de bloques en minas a cielo abierto, el cual consiste en definir cómo serán extraídas y procesadas cada una de las partes de un yacimiento, las cuales son explotadas por períodos, que a su vez permiten la construcción de un plan de producción. Este trabajo presenta una solución mediante algoritmos genéticos y su aplicación a instancias de pequeño y gran tamaño. Mediante agrupación a través de clustering y usando conos truncados como espacio de búsqueda para el AGP, se generan fases de extracción, respetando restricciones de talud. La evaluación de cada individuo se realiza usando el enfoque best-case, el cual extrae el mineral fase a fase, respetando las capacidades de minado y de procesamiento, para generar períodos que maximizan la valorización económica. Finalmente, el algoritmo es aplicado a un conjunto de instancias reales de dominio público, de forma paralela y distribuída, mediante el uso del clúster Leftraru, mostrando la flexibilidad del enfoque planteado. Los resultados del experimento muestran que la aplicación de AGP al problema estudiado permite encontrar soluciones de buena calidad en tiempos de ejecución aceptables, consideran- do la complejidad del problema. No obstante, se recomienda el uso de otros enfoques para la evaluación de los individuos, a fin de acelerar el proceso de búsqueda. | N63: https://usach.primo.exlibrisgroup.com/discovery/delivery/56USACH_INST:REPOSITORIO/1226478470006116 | O63: UNIVERSIDAD DE SANTIAGO DE CHILE | P63: DEPARTAMENTO DE INGENIERÍA INFORMÁTICA | Q63: (7) Computer Science | R63: (11) Parallel and Distributed Computing | S63: agp, mediante, problema, algoritmo, aplicación, búsqueda, cada, enfoque, evaluación, fase | T63: (19) Research/Investigation
A64: ANDRÉS MAURICIO SARMIENTO ADAROS | B64: - | D64: MAGÍSTER EN SEGURIDAD, PERITAJE Y AUDITORÍA EN PROCESOS INFORMÁTICOS | E64: ROGERS ATERO MONTES | G64: Propuesta de un modelo de plan de auditoría de seguridad para plataformas Unix y Linux | H64: 2015 | I64: Creative Commons AtribuciónNoComercialSinDerivadas | J64: AUTORIZADO | K64: SI | L64: =IF(K64 = "SI", EXTRA!$C$3, EXTRA!$C$4) | M64: El presente trabajo, desarrolla una investigación metodológica, y genera la propuesta de un modelo de Plan de Auditoría de Seguridad (PAS), para la realización de auditorías de seguridad sobre plataformas Unix y Linux, considerando al Sistema Operativo Unix (SOU), acompañado de su variante Linux (SOL). SOU es uno de los más exitosos de todos los tiempos, lo que es reconocido además porque este tipo de plataforma, es utilizada en una variedad de organizaciones a nivel mundial. De acuerdo a la investigación realizada, es posible constatar que mediante la utilización de un adecuado PAS, que integra un programa de revisión sistemático sobre plataformas Unix y Linux, un profesional auditor puede mejorar significativamente el proceso de identificación de configuraciones inseguras de un SOU/SOL, mediante diagnóstico y posterior documentación, enmarcado en un proceso general de auditoría. En la investigación se utilizan artefactos de software, implementadas mediante técnicas de scripting (mediante Bash), lo que permiten automatizar la extracción de información, y documentación de los papeles de trabajo del auditor (mediante macros en Excel), permitiendo apoyar significativa y eficientemente, el proceso de revisión técnica de factores de Seguridad. A su vez, considerando la estrategia no invasiva del modelo, se disminuye la presencia de errores y potenciales impactos negativos, en la ejecución del proceso para la extracción de la información. Como parte de los resultados, se comprueba que estructurar la auditoría bajo una metodología PAS detallada, basada en automatización, sumado a las técnicas regulares procedimientos y normativas asociadas al plan de auditoría, permite una adecuada detección, identificación y sensibilización para diagnosticar y recomendar mitigación de las vulnerabilidades presentes en SOU y SOL. En este contexto, se espera que el resultado del presente trabajo, sirva como un modelo base, para la realización de auditorías más efectivas sobre SOU y SOL. | N64: https://usach.primo.exlibrisgroup.com/discovery/delivery/56USACH_INST:REPOSITORIO/1226582390006116 | O64: UNIVERSIDAD DE SANTIAGO DE CHILE | P64: DEPARTAMENTO DE INGENIERÍA INFORMÁTICA | Q64: (7) Computer Science | R64: (12) Security | S64: mediante, sou, auditoría, proceso, sol, investigación, linux, modelo, pas, seguridad | T64: (13) Software Security
A65: FELIPE IGNACIO GONZÁLEZ ALFARO | B65: - | D65: MAGÍSTER EN INGENIERÍA INFORMÁTICA | E65: FERNANDO RANNOU FUENTES | G65: Reconstrucción y visualización de imágenes tomográficas en GPU: interoperabilidad OpenGL y OpenCL | H65: 2015 | I65: Atribución Creative Commons | J65: AUTORIZADO | K65: SI | L65: =IF(K65 = "SI", EXTRA!$C$3, EXTRA!$C$4) | M65: El proceso de reconstrucción de imágenes tomográficas tiene como objetivo crear una imagen a partir de datos de proyección. Es un procedimiento complejo y computacionalmente costoso cuando el algoritmo de reconstrucción es del tipo iterativo. La calidad de la representación depende de gran manera del tipo de algoritmo utilizado. A su vez, los numerosos datos obtenidos para la reconstrucción obliga a optimizar la forma en que éstos se almacenan y se usan. Es aquí, donde se presentan las matrices dispersas (matriz en que la mayoría de sus datos son cero), las cuales presentan distintos formatos dependiendo de la distribución de los valores distintos de cero. El presente trabajo muestra un estudio del procesos de reconstrucción de imagen en GPU y la relación de este proceso con el formato de la matriz dispersa en el que se almacenan los datos de la imagen utilizando dos de los formatos más comunes. Además, se presenta un nuevo paso de visualización de la imagen resultante durante el proceso de reconstrucción. El rendimiento computacional obtenido con la utilización del procesamiento paralelo en GPU muestra un speedup de 2,09 para el formato CSR, y 2.7 con la optimización de este formato. Para el formato COO, el más lento de todos, el speedup fue de 0,18, muy por debajo de lo esperado. | N65: https://usach.primo.exlibrisgroup.com/discovery/delivery/56USACH_INST:REPOSITORIO/1226638540006116 | O65: UNIVERSIDAD DE SANTIAGO DE CHILE | P65: DEPARTAMENTO DE INGENIERÍA INFORMÁTICA | Q65: (7) Computer Science | R65: (11) Parallel and Distributed Computing | S65: reconstrucción, datos, formato, imagen, proceso, algoritmo, almacenan, cero, distintos, formatos | T65: (2) Software Architecture
A66: GEOVANNA ALEXANDRA SUÁREZ GARCÍA | B66: - | D66: MAGÍSTER EN SEGURIDAD, PERITAJE Y AUDITORÍA EN PROCESOS INFORMÁTICOS | E66: ROGERS ATERO MONTES | G66: Metodología ágil de certificación forense y protección de datos personales almacenados en nube gratuita | H66: 2015 | I66: Creative Commons AtribuciónNoComercialCompartirIgual | J66: AUTORIZADO | K66: SI | L66: =IF(K66 = "SI", EXTRA!$C$3, EXTRA!$C$4) | M66: Esta tesis investiga una solución al problema de vulnerabilidades de seguridad de datos personales existentes en estructuras de nube gratuita, focalizando proteger y certificar, la confidencialidad e integridad de los datos, a través de una metodología basada en certificación forense y seguridad de datos personales, orientada al usuario dueño de esta información. Se desarrolla un esquema experimental, conformado por una cuenta y servicio de nube gratuita habilitado, un esquema de protección con certificación forense integrada en laptop propietario de ciber-acceso a nube, un inventario de datos personales típicos almacenables en nube y un dispositivo móvil para acciones experimentales de explotación de ciber-riesgos. En la investigación los datos almacenados son expuestos a ciber-vulnerabilidades experimentales de seguridad, análisis forense y de encriptación, utilizando una herramienta freeware1, con funcionalidades que permiten generar una solución de mitigación de riesgos, en torno a características reales de ciber-acceso a la nube gratuita, integrando y utilizando en la fase de pruebas reales, uno de los mayores proveedores de servicios de nube existente en el mercado. Los resultados experimentales obtenidos validan para un usuario, el desarrollo de una metodología ágil de seguridad y certificación forense de datos personales almacenables en nube gratuita, con acceso desde un laptop propietario, que brinda robustos niveles seguridad, permitiendo al usuario mantener protegida su información personal ante diversos tipos de ciber- ataques. Se demuestra experimentalmente que la metodología usuaria propuesta es ágil e integra a nivel usuario, protecciones de integridad y detección forense, ante un potencial ciber- delito sobre los datos usuarios almacenados en nube gratuita. El método de certificación forense planteado, integra identificación, preservación, análisis, y reporte, sirviendo como apoyo y guía efectiva, tanto para la implementación de seguridad de datos personales en nube gratuita, como para la detección forense de ataques, de tal manera que cada usuario, independiente del contrato con su proveedor de servicios de nube, pueda protegerse y tener una visión general de lo que ocurre con sus archivos personales, pudiendo tomar decisiones más informadas sobre la seguridad de los mismos en estructuras de nube gratuita cuyo uso se ha masificado a nivel mundial. | N66: https://usach.primo.exlibrisgroup.com/discovery/delivery/56USACH_INST:REPOSITORIO/1226573700006116 | O66: UNIVERSIDAD DE SANTIAGO DE CHILE | P66: DEPARTAMENTO DE INGENIERÍA INFORMÁTICA | Q66: (7) Computer Science | R66: (12) Security | S66: nube, datos, forense, gratuita, seguridad, ciber, personales, usuario, certificación, acceso | T66: (19) Research/Investigation
A67: CLAUDIO ANDRÉS MORALES ARAYA | B67: INGENIERÍA DE EJECUCIÓN EN COMPUTACIÓN E INFORMÁTICA | C67: DIURNA | E67: EDGARDO SEPÚLVEDA SARIEGO | G67: Diseño e implementación de ETL para servicios de leasing financiero y operativo | H67: 2015 | I67: SIN LICENCIA | J67: SIN AUTORIZACIÓN | K67: NO | L67: =IF(K67 = "SI", EXTRA!$C$3, EXTRA!$C$4) | N67: https://usach.primo.exlibrisgroup.com/discovery/delivery/56USACH_INST:REPOSITORIO/1240978610006116 | O67: UNIVERSIDAD DE SANTIAGO DE CHILE | P67: DEPARTAMENTO DE INGENIERÍA INFORMÁTICA | Q67: (28) It does not belong to the computer science field. | R67: (18) It does not belong to the computer science field. | S67: NA | T67: (20) It does not belong to the computer science field.
A68: DANIEL PEDRO PABLO WLADDIMIRO COTTET | B68: INGENIERÍA DE EJECUCIÓN EN COMPUTACIÓN E INFORMÁTICA | C68: DIURNA | D68: MAGÍSTER EN INGENIERÍA INFORMÁTICA | E68: NICOLÁS HIDALGO CASTILLO | F68: ERIKA ROSAS OLIVOS | G68: Modelo elástico de replicación de operadores para un sistema de procesamiento de Stream en tiempo real | H68: 2015 | I68: SIN LICENCIA | J68: SIN AUTORIZACIÓN | K68: NO | L68: =IF(K68 = "SI", EXTRA!$C$3, EXTRA!$C$4) | N68: https://usach.primo.exlibrisgroup.com/discovery/delivery/56USACH_INST:REPOSITORIO/1233008070006116 | O68: UNIVERSIDAD DE SANTIAGO DE CHILE | P68: DEPARTAMENTO DE INGENIERÍA INFORMÁTICA | Q68: (28) It does not belong to the computer science field. | R68: (18) It does not belong to the computer science field. | S68: NA | T68: (20) It does not belong to the computer science field.
A69: EDUARD ANTONIO MANTILLA TORRES | B69: - | D69: MAGÍSTER EN SEGURIDAD, PERITAJE Y AUDITORÍA EN PROCESOS INFORMÁTICOS | E69: ROGERS ATERO MONTES | G69: Estudio comparativo de índices de eficiencia para herramientas Freeware de Ethical Hacking aplicadas en Pentesting | H69: 2015 | I69: SIN LICENCIA | J69: SIN AUTORIZACIÓN | K69: NO | L69: =IF(K69 = "SI", EXTRA!$C$3, EXTRA!$C$4) | N69: https://usach.primo.exlibrisgroup.com/discovery/delivery/56USACH_INST:REPOSITORIO/1233007800006116 | O69: UNIVERSIDAD DE SANTIAGO DE CHILE | P69: DEPARTAMENTO DE INGENIERÍA INFORMÁTICA | Q69: (28) It does not belong to the computer science field. | R69: (18) It does not belong to the computer science field. | S69: NA | T69: (20) It does not belong to the computer science field.
A70: EMILIO ERNESTO TAPIA SANHUEZA | B70: INGENIERÍA CIVIL EN INFORMÁTICA | C70: DIURNA | D70: MAGÍSTER EN INGENIERÍA INFORMÁTICA | E70: JUAN MAURICIO MARÍN CAIHUAN | F70: GRACIELA VERÓNICA GIL COSTA | G70: Simulación paralela aproximada sobre S4 para motores de búsqueda web | H70: 2015 | I70: TODOS LOS DERECHOS RESERVADOS | J70: AUTORIZADO | K70: NO | L70: =IF(K70 = "SI", EXTRA!$C$3, EXTRA!$C$4) | N70: https://usach.primo.exlibrisgroup.com/discovery/delivery/56USACH_INST:REPOSITORIO/1226614520006116 | O70: UNIVERSIDAD DE SANTIAGO DE CHILE | P70: DEPARTAMENTO DE INGENIERÍA INFORMÁTICA | Q70: (28) It does not belong to the computer science field. | R70: (18) It does not belong to the computer science field. | S70: NA | T70: (20) It does not belong to the computer science field.
A71: ESTEBAN OMAR MANOSALVA RODRÍGUEZ | B71: INGENIERÍA CIVIL EN INFORMÁTICA | C71: DIURNA | E71: JUAN PABLO RUZ | F71: JOSÉ LUIS JARA VALENCIA | G71: Desarrollo de un asistente para el software Grei que permite guiar a los docentes en la creación de secuencias interactivas de aprendizaje resguardando criterios didácticos-matemáticos | H71: 2015 | I71: TODOS LOS DERECHOS RESERVADOS | J71: AUTORIZADO | K71: NO | L71: =IF(K71 = "SI", EXTRA!$C$3, EXTRA!$C$4) | N71: https://usach.primo.exlibrisgroup.com/discovery/delivery/56USACH_INST:REPOSITORIO/1226531340006116 | O71: UNIVERSIDAD DE SANTIAGO DE CHILE | P71: DEPARTAMENTO DE INGENIERÍA INFORMÁTICA | Q71: (28) It does not belong to the computer science field. | R71: (18) It does not belong to the computer science field. | S71: NA | T71: (20) It does not belong to the computer science field.
A72: FERNANDO ANTONIO GONZÁLEZ CASTRO | B72: INGENIERÍA CIVIL EN INFORMÁTICA | C72: DIURNA | E72: MARÍA CHAMORRO AHUMADA | G72: Implementación del proceso de formalización de subsidios de Corfo en Adobe Live Cycle | H72: 2015 | I72: TODOS LOS DERECHOS RESERVADOS | J72: AUTORIZADO | K72: NO | L72: =IF(K72 = "SI", EXTRA!$C$3, EXTRA!$C$4) | N72: https://usach.primo.exlibrisgroup.com/discovery/delivery/56USACH_INST:REPOSITORIO/1226580870006116 | O72: UNIVERSIDAD DE SANTIAGO DE CHILE | P72: DEPARTAMENTO DE INGENIERÍA INFORMÁTICA | Q72: (28) It does not belong to the computer science field. | R72: (18) It does not belong to the computer science field. | S72: NA | T72: (20) It does not belong to the computer science field.
A73: FREDY VÁSQUEZ VELA | B73: INGENIERÍA CIVIL EN INFORMÁTICA | C73: VESPERTINA | E73: MÓNICA VILLANUEVA ILUFI | G73: Planificación de entrega de pedidos de la empresa Marín | H73: 2015 | I73: TODOS LOS DERECHOS RESERVADOS | J73: AUTORIZADO | K73: NO | L73: =IF(K73 = "SI", EXTRA!$C$3, EXTRA!$C$4) | N73: https://usach.primo.exlibrisgroup.com/discovery/delivery/56USACH_INST:REPOSITORIO/1226522630006116 | O73: UNIVERSIDAD DE SANTIAGO DE CHILE | P73: DEPARTAMENTO DE INGENIERÍA INFORMÁTICA | Q73: (28) It does not belong to the computer science field. | R73: (18) It does not belong to the computer science field. | S73: NA | T73: (20) It does not belong to the computer science field.
A74: GONZALO EDUARDO QUEZADA MORAGA | B74: INGENIERÍA DE EJECUCIÓN EN COMPUTACIÓN E INFORMÁTICA | C74: VESPERTINA | E74: LUIS RÍOS SEPÚLVEDA | G74: Sistema de despacho para Cuerpo de Bomberos | H74: 2015 | I74: SIN LICENCIA | J74: SIN AUTORIZACIÓN | K74: NO | L74: =IF(K74 = "SI", EXTRA!$C$3, EXTRA!$C$4) | N74: https://usach.primo.exlibrisgroup.com/discovery/delivery/56USACH_INST:REPOSITORIO/1241018440006116 | O74: UNIVERSIDAD DE SANTIAGO DE CHILE | P74: DEPARTAMENTO DE INGENIERÍA INFORMÁTICA | Q74: (28) It does not belong to the computer science field. | R74: (18) It does not belong to the computer science field. | S74: NA | T74: (20) It does not belong to the computer science field.
A75: GUISSELLE CAROLIN SEGOVIA GUZMÁN | B75: INGENIERÍA CIVIL EN INFORMÁTICA | C75: DIURNA | D75: MAGÍSTER EN INGENIERÍA INFORMÁTICA | E75: GONZALO ACUÑA LEIVA | G75: Clasificación predictiva del estado de criticidad de una flota de equipos pesados en minería | H75: 2015 | I75: SIN LICENCIA | J75: SIN AUTORIZACIÓN | K75: NO | L75: =IF(K75 = "SI", EXTRA!$C$3, EXTRA!$C$4) | N75: https://usach.primo.exlibrisgroup.com/discovery/delivery/56USACH_INST:REPOSITORIO/1241018740006116 | O75: UNIVERSIDAD DE SANTIAGO DE CHILE | P75: DEPARTAMENTO DE INGENIERÍA INFORMÁTICA | Q75: (28) It does not belong to the computer science field. | R75: (18) It does not belong to the computer science field. | S75: NA | T75: (20) It does not belong to the computer science field.
A76: HÉCTOR MANUEL OPAZO ROBLES | B76: INGENIERÍA CIVIL EN INFORMÁTICA | C76: DIURNA | E76: ROSA MUÑOZ CALANCHIE | G76: Rentabilidad de costos de los fondos mutuos en Chile : un sistema de cálculo, visualización y comparación de información financiera | H76: 2015 | I76: TODOS LOS DERECHOS RESERVADOS | J76: SIN AUTORIZACIÓN | K76: NO | L76: =IF(K76 = "SI", EXTRA!$C$3, EXTRA!$C$4) | N76: https://usach.primo.exlibrisgroup.com/discovery/delivery/56USACH_INST:REPOSITORIO/1226532900006116 | O76: UNIVERSIDAD DE SANTIAGO DE CHILE | P76: DEPARTAMENTO DE INGENIERÍA INFORMÁTICA | Q76: (28) It does not belong to the computer science field. | R76: (18) It does not belong to the computer science field. | S76: NA | T76: (20) It does not belong to the computer science field.
A77: JOHN ISRAEL SALVO REYES | B77: INGENIERÍA DE EJECUCIÓN EN COMPUTACIÓN E INFORMÁTICA | C77: DIURNA | E77: ANDRÉS RICE MORA | G77: Automatización del proceso para visado de pago a proveedores de la empresa Envases del Pacífico (EDELPA) | H77: 2015 | I77: TODOS LOS DERECHOS RESERVADOS | J77: AUTORIZADO | K77: NO | L77: =IF(K77 = "SI", EXTRA!$C$3, EXTRA!$C$4) | N77: https://usach.primo.exlibrisgroup.com/discovery/delivery/56USACH_INST:REPOSITORIO/1226540550006116 | O77: UNIVERSIDAD DE SANTIAGO DE CHILE | P77: DEPARTAMENTO DE INGENIERÍA INFORMÁTICA | Q77: (28) It does not belong to the computer science field. | R77: (18) It does not belong to the computer science field. | S77: NA | T77: (20) It does not belong to the computer science field.
A78: JOSÉ ANTONIO ARCE PAREDES | B78: INGENIERÍA DE EJECUCIÓN EN COMPUTACIÓN E INFORMÁTICA | C78: VESPERTINA | E78: ROSA MUÑOZ CALANCHIE | G78: Sistema gestor de campañas comerciales con informes de control y seguimiento para empresas Ripley | H78: 2015 | I78: TODOS LOS DERECHOS RESERVADOS | J78: SIN AUTORIZACIÓN | K78: NO | L78: =IF(K78 = "SI", EXTRA!$C$3, EXTRA!$C$4) | N78: https://usach.primo.exlibrisgroup.com/discovery/delivery/56USACH_INST:REPOSITORIO/1241018500006116 | O78: UNIVERSIDAD DE SANTIAGO DE CHILE | P78: DEPARTAMENTO DE INGENIERÍA INFORMÁTICA | Q78: (28) It does not belong to the computer science field. | R78: (18) It does not belong to the computer science field. | S78: NA | T78: (20) It does not belong to the computer science field.
A79: JOSÉ LUIS VARELA OTÁROLA | B79: INGENIERÍA CIVIL EN INFORMÁTICA | C79: DIURNA | D79: MAGÍSTER EN INGENIERÍA INFORMÁTICA | E79: ROBERTO GONZÁLEZ-IBÁÑEZ | G79: Evaluación de la interacción con objetos de información digital utilizando una interfaz operada mediante gestos corporales | H79: 2015 | I79: TODOS LOS DERECHOS RESERVADOS | J79: AUTORIZADO | K79: NO | L79: =IF(K79 = "SI", EXTRA!$C$3, EXTRA!$C$4) | N79: https://usach.primo.exlibrisgroup.com/discovery/delivery/56USACH_INST:REPOSITORIO/1226597430006116 | O79: UNIVERSIDAD DE SANTIAGO DE CHILE | P79: DEPARTAMENTO DE INGENIERÍA INFORMÁTICA | Q79: (28) It does not belong to the computer science field. | R79: (18) It does not belong to the computer science field. | S79: NA | T79: (20) It does not belong to the computer science field.
A80: JOSE MIGUEL CORNEJO SOTO | B80: INGENIERÍA DE EJECUCIÓN EN COMPUTACIÓN E INFORMÁTICA | C80: VESPERTINA | E80: CAROLINA BONACIC CASTRO | G80: Sistema de apoyo a la captura de datos y determinación del rendimiento de cosechas en agricultura de precisión | H80: 2015 | I80: TODOS LOS DERECHOS RESERVADOS | J80: AUTORIZADO | K80: NO | L80: =IF(K80 = "SI", EXTRA!$C$3, EXTRA!$C$4) | N80: https://usach.primo.exlibrisgroup.com/discovery/delivery/56USACH_INST:REPOSITORIO/1226508770006116 | O80: UNIVERSIDAD DE SANTIAGO DE CHILE | P80: DEPARTAMENTO DE INGENIERÍA INFORMÁTICA | Q80: (28) It does not belong to the computer science field. | R80: (18) It does not belong to the computer science field. | S80: NA | T80: (20) It does not belong to the computer science field.
A81: JUAN ANDRÉS LEVICHE HUILIPÁN | B81: INGENIERÍA DE EJECUCIÓN EN COMPUTACIÓN E INFORMÁTICA | C81: DIURNA | E81: ALCIDES QUISPE SANCA | G81: Diseño de un sistema de operación TI basado en ITILv3 2011 para la empresa Akzio Consultores | H81: 2015 | I81: TODOS LOS DERECHOS RESERVADOS | J81: SIN AUTORIZACIÓN | K81: NO | L81: =IF(K81 = "SI", EXTRA!$C$3, EXTRA!$C$4) | N81: https://usach.primo.exlibrisgroup.com/discovery/delivery/56USACH_INST:REPOSITORIO/1241018560006116 | O81: UNIVERSIDAD DE SANTIAGO DE CHILE | P81: DEPARTAMENTO DE INGENIERÍA INFORMÁTICA | Q81: (28) It does not belong to the computer science field. | R81: (18) It does not belong to the computer science field. | S81: NA | T81: (20) It does not belong to the computer science field.
A82: JUAN CARLOS VARGAS GODOY | B82: INGENIERÍA CIVIL EN INFORMÁTICA | C82: DIURNA | D82: MAGÍSTER EN INGENIERÍA INFORMÁTICA | E82: ROBERTO GONZÁLEZ-IBÁÑEZ | G82: Evaluación implícita de carga mental de trabajo durante el procesamiento de información a partir de registros oculares | H82: 2015 | I82: TODOS LOS DERECHOS RESERVADOS | J82: AUTORIZADO | K82: NO | L82: =IF(K82 = "SI", EXTRA!$C$3, EXTRA!$C$4) | N82: https://usach.primo.exlibrisgroup.com/discovery/delivery/56USACH_INST:REPOSITORIO/1226599050006116 | O82: UNIVERSIDAD DE SANTIAGO DE CHILE | P82: DEPARTAMENTO DE INGENIERÍA INFORMÁTICA | Q82: (28) It does not belong to the computer science field. | R82: (18) It does not belong to the computer science field. | S82: NA | T82: (20) It does not belong to the computer science field.
A83: JUAN FERNANDO MEJÍA CALLE | B83: - | D83: MAGÍSTER EN SEGURIDAD, PERITAJE Y AUDITORÍA EN PROCESOS INFORMÁTICOS | E83: JUAN IGNACIO ITURBE ARAYA | G83: Modelo de proceso para análisis, caracterización y clasificación de archivos ejecutables potencialmente maliciosos en un entorno organizacional con sistema operativo Windows | H83: 2015 | I83: TODOS LOS DERECHOS RESERVADOS | J83: AUTORIZADO | K83: NO | L83: =IF(K83 = "SI", EXTRA!$C$3, EXTRA!$C$4) | M83: Actualmente los ataques de seguridad de la información son protagonizados, en su mayoría, por software malicioso, pudiendo provocar en una empresa pérdidas económicas, comprometer información, afectar la continuidad del negocio y/o reputación o recibir chantajes. Existen técnicas para analizar estos archivos maliciosos y sus características, con el objetivo de determinar su propósito y funcionalidad. Estas características se dividen en estáticas, cuando se extraen sin ejecutar el archivo y dinámicas, si se ejecuta el mismo. En ocasiones, es necesario analizar archivos ejecutables en caso de ataques de posibles malware que no sean reconocidos por antivirus, la necesidad de conocer las características de funcionamiento de archivos potencialmente maliciosos o la falta de un marco referencial para análisis de archivos ejecutables, para mejorar la seguridad de una organización, o como parte de alguna investigación forense. En el presente trabajo se propone un modelo de proceso para realizar análisis de archivos ejecutables, integrando características estáticas y dinámicas y definiendo fases, actividades, herramientas, entradas, salidas y actores. Inicialmente se hace una revisión de literatura a cerca de técnicas de análisis de malware. Luego se ha seleccionado las características estáticas y dinámicas más significativas para proponer un proceso de análisis. Se procedió a aplicar este modelo a un conjunto de archivos, maliciosos y limpios, para alimentar un software con métodos de clasificación: RF, IB1 y DT. Por último, se aplicó este modelo a varios archivos ejecutables. Luego de aplicado este modelo, se obtuvo 91% de efectividad de clasificación con el método RF y, aplicando este modelo a nueve archivos ejecutables, el modelo predijo efectivamente a ocho archivos con un grado de certeza alto lo cual demuestra que el proceso presentado puede resultar exitoso en un entorno real, a sabiendas que puede ser mejorado. | N83: https://usach.primo.exlibrisgroup.com/discovery/delivery/56USACH_INST:REPOSITORIO/1226476280006116 | O83: UNIVERSIDAD DE SANTIAGO DE CHILE | P83: DEPARTAMENTO DE INGENIERÍA INFORMÁTICA | Q83: (7) Computer Science | R83: (12) Security | S83: archivos, modelo, características, ejecutables, análisis, dinámicas, estáticas, maliciosos, proceso, analizar | T83: (5) Software Testing
A84: JUAN LUIS JESÚS MARCHANT AGUILAR | B84: INGENIERÍA DE EJECUCIÓN EN COMPUTACIÓN E INFORMÁTICA | C84: VESPERTINA | E84: CAROLINA BONACIC CASTRO | G84: Sistema de seguimiento de prospectos y clientes de una empresa Informática | H84: 2015 | I84: SIN LICENCIA | J84: SIN AUTORIZACIÓN | K84: NO | L84: =IF(K84 = "SI", EXTRA!$C$3, EXTRA!$C$4) | N84: https://usach.primo.exlibrisgroup.com/discovery/delivery/56USACH_INST:REPOSITORIO/1241018620006116 | O84: UNIVERSIDAD DE SANTIAGO DE CHILE | P84: DEPARTAMENTO DE INGENIERÍA INFORMÁTICA | Q84: (28) It does not belong to the computer science field. | R84: (18) It does not belong to the computer science field. | S84: NA | T84: (20) It does not belong to the computer science field.
A85: MARCO ALEJANDRO BAEZA SALAZAR | B85: INGENIERÍA CIVIL EN INFORMÁTICA | C85: DIURNA | E85: CAROLINA BONACIC CASTRO | G85: Sistema de creación y personalización de actividades educativas para alumnos con necesidades especiales transitorias | H85: 2015 | I85: TODOS LOS DERECHOS RESERVADOS | J85: AUTORIZADO | K85: NO | L85: =IF(K85 = "SI", EXTRA!$C$3, EXTRA!$C$4) | N85: https://usach.primo.exlibrisgroup.com/discovery/delivery/56USACH_INST:REPOSITORIO/1226605290006116 | O85: UNIVERSIDAD DE SANTIAGO DE CHILE | P85: DEPARTAMENTO DE INGENIERÍA INFORMÁTICA | Q85: (28) It does not belong to the computer science field. | R85: (18) It does not belong to the computer science field. | S85: NA | T85: (20) It does not belong to the computer science field.
A86: MARÍA JOSÉ OSORIO SOTO | B86: INGENIERÍA CIVIL EN INFORMÁTICA | C86: DIURNA | E86: ROSA MUÑOZ CALANCHIE | G86: Objeto de aprendizaje web como apoyo al capítulo de autocuidado del curso Taller de Desarrollo Personal para Ingeniería | H86: 2015 | I86: TODOS LOS DERECHOS RESERVADOS | J86: AUTORIZADO | K86: NO | L86: =IF(K86 = "SI", EXTRA!$C$3, EXTRA!$C$4) | N86: https://repositorio.usach.cl/discovery/delivery/56USACH_INST:REPOSITORIO/1226614700006116 | O86: UNIVERSIDAD DE SANTIAGO DE CHILE | P86: DEPARTAMENTO DE INGENIERÍA INFORMÁTICA | Q86: (28) It does not belong to the computer science field. | R86: (18) It does not belong to the computer science field. | S86: NA | T86: (20) It does not belong to the computer science field.
A87: PABLO ANDRÉS CISTERNA CÁRCAMO | B87: INGENIERÍA DE EJECUCIÓN EN COMPUTACIÓN E INFORMÁTICA | C87: VESPERTINA | E87: LUIS RÍOS SEPÚLVEDA | G87: Sistema para la planificación y control de los procesos productivos del Departamento de Pre-impresión de Quad/Graphics Chile | H87: 2015 | I87: TODOS LOS DERECHOS RESERVADOS | J87: AUTORIZADO | K87: NO | L87: =IF(K87 = "SI", EXTRA!$C$3, EXTRA!$C$4) | N87: https://usach.primo.exlibrisgroup.com/discovery/delivery/56USACH_INST:REPOSITORIO/1226490760006116 | O87: UNIVERSIDAD DE SANTIAGO DE CHILE | P87: DEPARTAMENTO DE INGENIERÍA INFORMÁTICA | Q87: (28) It does not belong to the computer science field. | R87: (18) It does not belong to the computer science field. | S87: NA | T87: (20) It does not belong to the computer science field.
A88: PABLO IGNACIO GONZÁLEZ CANTERGIANI | B88: - | D88: MAGÍSTER EN INGENIERÍA INFORMÁTICA | E88: CAROLINA BONACIC CASTRO | G88: Una solución híbrida de balance de carga para el sistema de procesamiento de stream S4 | H88: 2015 | I88: SIN LICENCIA | J88: SIN AUTORIZACIÓN | K88: NO | L88: =IF(K88 = "SI", EXTRA!$C$3, EXTRA!$C$4) | N88: https://usach.primo.exlibrisgroup.com/discovery/delivery/56USACH_INST:REPOSITORIO/1232493650006116 | O88: UNIVERSIDAD DE SANTIAGO DE CHILE | P88: DEPARTAMENTO DE INGENIERÍA INFORMÁTICA | Q88: (28) It does not belong to the computer science field. | R88: (18) It does not belong to the computer science field. | S88: NA | T88: (20) It does not belong to the computer science field.
A89: RAMIRO ALEXANDER GONZAGA BUSTAMANTE | B89: - | D89: MAGÍSTER EN SEGURIDAD, PERITAJE Y AUDITORÍA EN PROCESOS INFORMÁTICOS | E89: ROSA MUÑOZ CALANCHIE | G89: Cálculo de la seguridad real de la infraestructura tecnológica de una institución financiera mediante un test de penetración Caja Blanca basado en OSSTMM | H89: 2015 | I89: TODOS LOS DERECHOS RESERVADOS | J89: SIN AUTORIZACIÓN | K89: NO | L89: =IF(K89 = "SI", EXTRA!$C$3, EXTRA!$C$4) | N89: https://usach.primo.exlibrisgroup.com/discovery/delivery/56USACH_INST:REPOSITORIO/1249698470006116 | O89: UNIVERSIDAD DE SANTIAGO DE CHILE | P89: DEPARTAMENTO DE INGENIERÍA INFORMÁTICA | Q89: (28) It does not belong to the computer science field. | R89: (18) It does not belong to the computer science field. | S89: NA | T89: (20) It does not belong to the computer science field.
A90: SERGIO ANDRÉS FUENTES MÜLLER | B90: INGENIERÍA DE EJECUCIÓN EN COMPUTACIÓN E INFORMÁTICA | C90: VESPERTINA | E90: ROSA MUÑOZ CALANCHIE | G90: Software de prevención de la inyección de código malicioso en aplicaciones Web | H90: 2015 | I90: SIN LICENCIA | J90: SIN AUTORIZACIÓN | K90: NO | L90: =IF(K90 = "SI", EXTRA!$C$3, EXTRA!$C$4) | N90: https://usach.primo.exlibrisgroup.com/discovery/delivery/56USACH_INST:REPOSITORIO/1226517580006116 | O90: UNIVERSIDAD DE SANTIAGO DE CHILE | P90: DEPARTAMENTO DE INGENIERÍA INFORMÁTICA | Q90: (28) It does not belong to the computer science field. | R90: (18) It does not belong to the computer science field. | S90: NA | T90: (20) It does not belong to the computer science field.
A91: VÍCTOR DANIEL ERICES NEIRA | B91: INGENIERÍA CIVIL EN INFORMÁTICA | C91: VESPERTINA | E91: BRUNO JERARDINO WIESENBORN | G91: Utilización de una metodología ágil para la gestión de proyectos TI para ENTEL SA | H91: 2015 | I91: TODOS LOS DERECHOS RESERVADOS | J91: AUTORIZADO | K91: NO | L91: =IF(K91 = "SI", EXTRA!$C$3, EXTRA!$C$4) | N91: https://usach.primo.exlibrisgroup.com/discovery/delivery/56USACH_INST:REPOSITORIO/1226459870006116 | O91: UNIVERSIDAD DE SANTIAGO DE CHILE | P91: DEPARTAMENTO DE INGENIERÍA INFORMÁTICA | Q91: (28) It does not belong to the computer science field. | R91: (18) It does not belong to the computer science field. | S91: NA | T91: (20) It does not belong to the computer science field.
A92: WILLIAMS JOHN SOZA IBARRA | B92: INGENIERÍA CIVIL EN INFORMÁTICA | C92: VESPERTINA | E92: MÓNICA VILLANUEVA ILUFI | F92: LUCIANO HIDALGO SEPÚLVEDA | G92: Sistema de gestión docente del Departamento de Ingeniería Informática de la Universidad de Santiago de Chile módulo: Inscripción de asignaturas | H92: 2015 | I92: TODOS LOS DERECHOS RESERVADOS | J92: AUTORIZADO | K92: NO | L92: =IF(K92 = "SI", EXTRA!$C$3, EXTRA!$C$4) | N92: https://usach.primo.exlibrisgroup.com/discovery/delivery/56USACH_INST:REPOSITORIO/1226601890006116 | O92: UNIVERSIDAD DE SANTIAGO DE CHILE | P92: DEPARTAMENTO DE INGENIERÍA INFORMÁTICA | Q92: (28) It does not belong to the computer science field. | R92: (18) It does not belong to the computer science field. | S92: NA | T92: (20) It does not belong to the computer science field.
A93: GARY IGNACIO FUENZALIDA NAVARRETE | B93: - | D93: MAGÍSTER EN INGENIERÍA INFORMÁTICA | E93: ROBERTO GONZÁLEZ-IBÁÑEZ | G93: Evaluación de representaciones de resultados de búsqueda de información | H93: 2015 | I93: TODOS LOS DERECHOS RESERVADOS | J93: SIN AUTORIZACIÓN | K93: NO | L93: =IF(K93 = "SI", EXTRA!$C$3, EXTRA!$C$4) | N93: https://usach.primo.exlibrisgroup.com/discovery/delivery/56USACH_INST:REPOSITORIO/1240978550006116 | O93: UNIVERSIDAD DE SANTIAGO DE CHILE | P93: DEPARTAMENTO DE INGENIERÍA INFORMÁTICA | Q93: (28) It does not belong to the computer science field. | R93: (18) It does not belong to the computer science field. | S93: NA | T93: (20) It does not belong to the computer science field.
A94: RODRIGO ANDRÉS YÁÑEZ GUTIÉRREZ | B94: INGENIERÍA DE EJECUCIÓN EN COMPUTACIÓN E INFORMÁTICA | C94: DIURNA | E94: ROSA MUÑOZ CALANCHIE | G94: Objetos de aprendizaje sobre la gestión de proyectos de tecnologías de la información | H94: 2015 | I94: Creative Commons AtribuciónNoComercial | J94: AUTORIZADO | K94: SI | L94: =IF(K94 = "SI", EXTRA!$C$3, EXTRA!$C$4) | M94: Un alto porcentaje de los profesionales del área de Tecnologías de la Información no tienen las competencias necesarias para la gestión de proyectos que coordinan, es por esto que es necesaria la obtención de conocimientos del área para así poder reducir los altos índices de fracasos en los proyectos. Existen organizaciones como Project Management Institute (PMI) que mediante su libro PMBOK definen buenas prácticas para la Gestión de proyectos. En función de esto es que el presente Trabajo de Titulación busca apoyar a los profesionales del área de Ingeniería y personas interesadas, por medio del desarrollo de Objetos de aprendizajes (OA). Entiéndase por OA a la mínima estructura independiente que contiene un objetivo, una actividad de aprendizaje y un mecanismo de evaluación, el cual puede ser desarrollado con Tecnologías de la Información, de manera de posibilitar su reutilización, interoperabilidad, accesibilidad y duración en el tiempo. Los contenidos que abordan los Objetos de aprendizaje realizados son tres de las más importantes áreas de Gestión; Alcance, Tiempo y Costos, las cuales son llamadas de forma clásica como la Triple Restricción. Cada uno de los OA permite al usuario relacionarse de forma simple y general a cada uno de los contenidos pero además existe la opción de interiorizarse en cada uno de los procesos de cada área, presentando las entradas, herramientas y técnicas y las salidas de cada proceso. El desarrollo de cada uno de los Objetos de Aprendizaje es llevado a cabo bajo la metodología CPIS, concluyendo que cada una de las etapas de ésta es llevada a cabo de forma correcta. Los objetivos del trabajo fueron cumplidos, los contenidos han sido validados por un profesor experto del área y mediante Heurística de Nielsen se valida la usabilidad del OA. El trabajo desarrollado queda disponible para su uso en cursos del área. | N94: https://usach.primo.exlibrisgroup.com/discovery/delivery/56USACH_INST:REPOSITORIO/1226505690006116 | O94: UNIVERSIDAD DE SANTIAGO DE CHILE | P94: DEPARTAMENTO DE INGENIERÍA INFORMÁTICA | Q94: (7) Computer Science | R94: (14) Software Development Fundamentals | S94: cada, área, oa, aprendizaje, contenidos, forma, gestión, objetos, proyectos, trabajo | T94: (1) Software Requirements
A95: DANIEL MARIANO GACITÚA VÁSQUEZ | B95: INGENIERÍA DE EJECUCIÓN EN COMPUTACIÓN E INFORMÁTICA | C95: DIURNA | E95: ROBERTO GONZÁLEZ-IBÁÑEZ | G95: Neurone : sistema de apoyo para la evaluación de competencias de investigación en línea para estudiantes de enseñanza básica | H95: 2016 | I95: Atribución Creative Commons | J95: AUTORIZADO | K95: SI | L95: =IF(K95 = "SI", EXTRA!$C$3, EXTRA!$C$4) | M95: En la actualidad el uso de motores de búsqueda web para la búsqueda en grandes cuerpos de documentos se ha vuelto parte de la rutina diaria de navegación del usuario promedio. El rápido crecimiento que ha tenido Internet en los últimos años ha obligado incluso a los planteles educacionales a adaptarse e integrar el uso de documentos en línea para el aprendizaje. Al respecto, resulta de gran interés para ciertos grupos de investigación el conocer como la gente realiza sus búsquedas con el objetivo de estudiar sus patrones de comportamiento en línea y modelar su comportamiento. Al respecto, el Proyecto iFuCo (“Enhancing learning and teaching future competences of online inquiry in multiple domains”), formado por investigadores de Chile y Finlandia, desea investigar y modelar los comportamientos y competencias de investigación en línea de estudiantes de enseñanza básica. Para ello, necesita contar con datos e información de uso acerca de la navegación del estudiante. Este trabajo se dedica a documentar el desarrollo de NEURONE (oNlinE inqUiry expeRimentatiON systEm), una plataforma web que posibilita la captura de datos y otra información relevante de los comportamientos de los usuarios en ambientes de búsqueda en línea. Para lograr dicha captura, NEURONE ofrece un ambiente de búsqueda simulado y controlado, en el cual los usuarios deberán cumplir una serie de tareas asignadas mientras son rastreadas sus interacciones. Toda la información recopilada en NEURONE será utilizada como referencia para futuros estudios del tema. | N95: https://usach.primo.exlibrisgroup.com/discovery/delivery/56USACH_INST:REPOSITORIO/1226603970006116 | O95: UNIVERSIDAD DE SANTIAGO DE CHILE | P95: DEPARTAMENTO DE INGENIERÍA INFORMÁTICA | Q95: (7) Computer Science | R95: (16) Specialized Platform Development | S95: búsqueda, línea, información, neurone, uso, captura, comportamiento, comportamientos, datos, documentos | T95: (19) Research/Investigation
A96: ALEJANDRO ANDRÉS VALDÉS VALENZUELA | B96: INGENIERÍA DE EJECUCIÓN EN COMPUTACIÓN E INFORMÁTICA | C96: VESPERTINA | E96: JOSÉ ÁLVAREZ GUENCHUMAN | G96: Sistema de información sobre situación fitosanitaria en Chile | H96: 2016 | I96: TODOS LOS DERECHOS RESERVADOS | J96: SIN AUTORIZACIÓN | K96: NO | L96: =IF(K96 = "SI", EXTRA!$C$3, EXTRA!$C$4) | N96: https://usach.primo.exlibrisgroup.com/discovery/delivery/56USACH_INST:REPOSITORIO/1249641440006116 | O96: UNIVERSIDAD DE SANTIAGO DE CHILE | P96: DEPARTAMENTO DE INGENIERÍA INFORMÁTICA | Q96: (28) It does not belong to the computer science field. | R96: (18) It does not belong to the computer science field. | S96: NA | T96: (20) It does not belong to the computer science field.
A97: ALEJANDRO GERARDO ACEVEDO KALLENS | B97: INGENIERÍA DE EJECUCIÓN EN COMPUTACIÓN E INFORMÁTICA | C97: VESPERTINA | E97: RICARDO CONTRERAS SEPÚLVEDA | G97: Sistema de arriendo de insumos para la construcción para la Pyme Sociedad Comercial Gutiérrez & Lagos Ltda. | H97: 2016 | I97: SIN LICENCIA | J97: SIN AUTORIZACIÓN | K97: NO | L97: =IF(K97 = "SI", EXTRA!$C$3, EXTRA!$C$4) | N97: https://usach.primo.exlibrisgroup.com/discovery/delivery/56USACH_INST:REPOSITORIO/1249641150006116 | O97: UNIVERSIDAD DE SANTIAGO DE CHILE | P97: DEPARTAMENTO DE INGENIERÍA INFORMÁTICA | Q97: (28) It does not belong to the computer science field. | R97: (18) It does not belong to the computer science field. | S97: NA | T97: (20) It does not belong to the computer science field.
A98: ALEX IGNACIO PERAITA RODRÍGUEZ | B98: INGENIERÍA DE EJECUCIÓN EN COMPUTACIÓN E INFORMÁTICA | C98: VESPERTINA | E98: LUCIANO HIDALGO SEPÚLVEDA | F98: ALCIDES QUISPE SANCA | G98: Modelo de medición de madurez y plan de mejora en gestión de proyectos para un área TI del rubro servicios | H98: 2016 | I98: TODOS LOS DERECHOS RESERVADOS | J98: SIN AUTORIZACIÓN | K98: NO | L98: =IF(K98 = "SI", EXTRA!$C$3, EXTRA!$C$4) | N98: https://usach.primo.exlibrisgroup.com/discovery/delivery/56USACH_INST:REPOSITORIO/1249701540006116 | O98: UNIVERSIDAD DE SANTIAGO DE CHILE | P98: DEPARTAMENTO DE INGENIERÍA INFORMÁTICA | Q98: (28) It does not belong to the computer science field. | R98: (18) It does not belong to the computer science field. | S98: NA | T98: (20) It does not belong to the computer science field.
A99: ÁLVARO ANDRÉS ZÚÑIGA CABEZAS | B99: INGENIERÍA DE EJECUCIÓN EN COMPUTACIÓN E INFORMÁTICA | C99: DIURNA | E99: JUAN MAURICIO MARÍN CAIHUAN | G99: Construcción e integración de sistema CRM para compañía de retail | H99: 2016 | I99: TODOS LOS DERECHOS RESERVADOS | J99: SIN AUTORIZACIÓN | K99: NO | L99: =IF(K99 = "SI", EXTRA!$C$3, EXTRA!$C$4) | N99: https://usach.primo.exlibrisgroup.com/discovery/delivery/56USACH_INST:REPOSITORIO/1249698950006116 | O99: UNIVERSIDAD DE SANTIAGO DE CHILE | P99: DEPARTAMENTO DE INGENIERÍA INFORMÁTICA | Q99: (28) It does not belong to the computer science field. | R99: (18) It does not belong to the computer science field. | S99: NA | T99: (20) It does not belong to the computer science field.
A100: ANDREA DEL PILAR ANTOINE ROJO | B100: INGENIERÍA CIVIL EN INFORMÁTICA | C100: DIURNA | E100: LUIS BERRIOS PEÑA | G100: Marco de trabajo para la gestión de proyectos tecnológicos y aplicación en el proyecto de renovación tecnológica de los sistemas de radiocomunicaciones en el Metro de Santiago | H100: 2016 | I100: TODOS LOS DERECHOS RESERVADOS | J100: SIN AUTORIZACIÓN | K100: NO | L100: =IF(K100 = "SI", EXTRA!$C$3, EXTRA!$C$4) | N100: https://usach.primo.exlibrisgroup.com/discovery/delivery/56USACH_INST:REPOSITORIO/1241017500006116 | O100: UNIVERSIDAD DE SANTIAGO DE CHILE | P100: DEPARTAMENTO DE INGENIERÍA INFORMÁTICA | Q100: (28) It does not belong to the computer science field. | R100: (18) It does not belong to the computer science field. | S100: NA | T100: (20) It does not belong to the computer science field.
...

Sheet INFO_ACADEMICOS
A1: ACADEMICO | B1: CORREO | C1: IMAGEN
A2: ALCIDES QUISPE SANCA | B2: alcides.quispe@usach.cl | C2: https://informatica.usach.cl/wp-content/uploads/elementor/thumbs/AQ_f24-r2bm4c4gih5zub6v8qklm6p05ssarbmkz1mfevm0m8.png
A3: ALVARO YÁÑEZ CARRIZO | B3: alvaro.yanez@usach.cl | C3: https://informatica.usach.cl/wp-content/uploads/elementor/thumbs/WIN_20211118_11_39_04_Pro_r.jpg-r2bm3x31h4leojspok2kiahmnmufc5yvkz6nqg8bds.png
A4: ANDRÉS RICE MORA | B4: SIN CORREO INFORMADO | C4: https://informatica.usach.cl/wp-content/uploads/elementor/thumbs/no-foto-r2bm3yypusnzbrpzdkvtna0juel5rk6c98hmp05j1c.jpg
A5: ARTURO ÁLVAREZ CEA | B5: arturo.alvarez@usach.cl | C5: https://informatica.usach.cl/wp-content/uploads/elementor/thumbs/Arturo-Alvarez-miniatura-r2bm3y0vnymp05rcj2h72s9390psjv2lx3u57q6x7k.jpg
A6: ARTURO TERRA VÁSQUEZ | B6: arturo.terra@usach.cl | C6: https://informatica.usach.cl/wp-content/uploads/elementor/thumbs/Foto-ATV-r2bm3w57aak4cxu2u1nxxsq628z24gv58uj6969pk0.jpg
A7: BRUNO JERARDINO WIESENBORN | B7: SIN CORREO INFORMADO | C7: https://informatica.usach.cl/wp-content/uploads/elementor/thumbs/no-foto-r2bm3yypusnzbrpzdkvtna0juel5rk6c98hmp05j1c.jpg
A8: CARLOS GONZÁLEZ CORTÉS | B8: carlos.gonzalez.c@usach.cl | C8: https://informatica.usach.cl/wp-content/uploads/elementor/thumbs/3625427834v28vc872b827-r4r2gkzfh5f31g5qt6l8vo3usr50pdjq56ffwqwcyo.png
A9: CAROLINA BONACIC CASTRO | B9: carolina.bonacic@usach.cl | C9: https://informatica.usach.cl/wp-content/uploads/elementor/thumbs/654735476563-r2bm3yypusnzbrpzdkvtna0juel5rk6c98hmp05j1c.png
A10: CRISTÓBAL ACOSTA JURADO | B10: cristobal.acosta@usach.cl | C10: https://informatica.usach.cl/wp-content/uploads/elementor/thumbs/cristobal-acosta-miniatura-r2bm3y0vnymp05rcj2h72s9390psjv2lx3u57q6x7k.png
A11: DANIEL VEGA ARAYA | B11: SIN CORREO INFORMADO | C11: https://informatica.usach.cl/wp-content/uploads/elementor/thumbs/no-foto-r2bm3yypusnzbrpzdkvtna0juel5rk6c98hmp05j1c.jpg
A12: DIEGO CARO ALARCÓN | B12: SIN CORREO INFORMADO | C12: https://informatica.usach.cl/wp-content/uploads/elementor/thumbs/no-foto-r2bm3yypusnzbrpzdkvtna0juel5rk6c98hmp05j1c.jpg
... A59: VIOLETA CHANG CAMACHO | B59: violeta.chang@usach.cl | C59: https://informatica.usach.cl/wp-content/uploads/elementor/thumbs/violeta_chang-r2bm3yypusnzbrpzdkvtna0juel5rk6c98hmp05j1c.png

Sheet EXTRA
B2: VALOR | C2: RESULTADO
B3: SI
B4: NO
